{
    "civilization": "French",
    "name": "knights archers",
    "author": "Beastyqt",
    "source": "https://www.youtube.com/watch?v=N7oxp5O-wrg",
    "build_order": [{
            "population_count": 10,
            "villager_count": 8,
            "age": 1,
            "resources": {
                "food": 8,
                "wood": 0,
                "gold": 0,
                "stone": 0
            },
            "notes": [
                "Send the first 6 @unit_worker/villager.png@ to @resource/sheep.png@. Make an additional @unit_cavalry/scout.png@.",
                "Send the next 2 @unit_worker/villager.png@ to @resource/sheep.png@ (8 in total). Build a @building_economy/house.png@."
            ]
        },
        {
            "population_count": 13,
            "villager_count": 11,
            "age": 1,
            "resources": {
                "food": 8,
                "wood": 0,
                "gold": 3,
                "stone": 0
            },
            "notes": [
                "Send the next 3 @unit_worker/villager.png@ to @resource/resource_gold.png@."
            ]
        },
        {
            "population_count": 16,
            "villager_count": 14,
            "age": 1,
            "resources": {
                "food": 8,
                "wood": 3,
                "gold": 3,
                "stone": 0
            },
            "notes": [
                "Send the next 3 @unit_worker/villager.png@ to @resource/resource_wood.png@. Build @landmark_french/school-of-cavalry.png@ with 3 @unit_worker/villager.png@ from @resource/resource_food.png@."
            ]
        },
        {
            "population_count": 18,
            "villager_count": 16,
            "age": 1,
            "resources": {
                "food": 5,
                "wood": 5,
                "gold": 3,
                "stone": 0
            },
            "notes": [
                "Build a @building_economy/mill.png@ with the next @unit_worker/villager.png@ and a @building_economy/house.png@ with the next one.",
                "Send them both to @resource/resource_wood.png@ after construction."
            ]
        },
        {
            "population_count": 22,
            "villager_count": 20,
            "age": 1,
            "resources": {
                "food": 9,
                "wood": 5,
                "gold": 3,
                "stone": 0
            },
            "notes": [
                "Send the next @unit_worker/villager.png@ to @resource/resource_food.png@. Research @technology_economy/wheelbarrow.png@."
            ]
        },
        {
            "population_count": 28,
            "villager_count": 24,
            "age": 2,
            "resources": {
                "food": 13,
                "wood": 5,
                "gold": 6,
                "stone": 0
            },
            "notes": [
                "Once in @age/age_2.png@, send the 3 @unit_worker/villager.png@ on @landmark_french/school-of-cavalry.png@ to @resource/resource_gold.png@.",
                "Build an @building_military/archery-range.png@ and start training @unit_french/royal-knight-2.png@ and @unit_infantry/archer-2.png@.",
                "Continue sending @unit_worker/villager.png@ to @resource/resource_food.png@ (up to 13)."
            ]
        },
        {
            "population_count": 47,
            "villager_count": 32,
            "age": 2,
            "resources": {
                "food": 13,
                "wood": 13,
                "gold": 6,
                "stone": 0
            },
            "notes": [
                "Build a @building_technology/blacksmith.png@, send the next @unit_worker/villager.png@ to @resource/resource_wood.png@.",
                "Continue training @unit_french/royal-knight-2.png@ and @unit_infantry/archer-2.png@. Research @technology_military/steeled-arrow.png@ and @technology_military/iron-undermesh.png@."
            ]
        },
        {
            "population_count": -1,
            "villager_count": -1,
            "age": 2,
            "resources": {
                "food": -1,
                "wood": -1,
                "gold": -1,
                "stone": 0
            },
            "notes": [
                "Continue adding @unit_worker/villager.png@ to @resource/resource_food.png@, @resource/resource_wood.png@ and @resource/resource_gold.png@ (9).",
                "Add second @building_military/stable.png@ and @building_military/archery-range.png@. Research @technology_economy/double-broadaxe.png@, @technology_economy/specialized-pick.png@, @technology_economy/horticulture.png@...",
                "Research @technology_french/chivalry.png@ when several @unit_french/royal-knight-2.png@ are damaged."
            ]
        }
    ]
}