{
    "civilization": "French",
    "name": "2 town centers",
    "author": "DivineDFP",
    "source": "https://www.youtube.com/watch?v=lqkbyIwvMT8",
    "build_order": [{
            "population_count": 8,
            "villager_count": 7,
            "age": 1,
            "resources": {
                "food": 7,
                "wood": 0,
                "gold": 0,
                "stone": 0
            },
            "notes": [
                "Send the first 6 @unit_worker/villager.png@ to @resource/sheep.png@.",
                "Send the next @unit_worker/villager.png@ also to @resource/sheep.png@ (7 in total)."
            ]
        },
        {
            "population_count": 11,
            "villager_count": 10,
            "age": 1,
            "resources": {
                "food": 7,
                "wood": 0,
                "gold": 3,
                "stone": 0
            },
            "notes": [
                "Send the next 3 @unit_worker/villager.png@ to @resource/resource_gold.png@.",
                "Build a @building_economy/house.png@ with a @unit_worker/villager.png@ from @resource/resource_gold.png@."
            ]
        },
        {
            "population_count": 16,
            "villager_count": 15,
            "age": 1,
            "resources": {
                "food": 7,
                "wood": 5,
                "gold": 3,
                "stone": 0
            },
            "notes": [
                "Send the next 5 @unit_worker/villager.png@ to @resource/resource_wood.png@."
            ]
        },
        {
            "population_count": 17,
            "villager_count": 16,
            "age": 1,
            "resources": {
                "food": 6,
                "wood": 5,
                "gold": 3,
                "stone": 1
            },
            "notes": [
                "The next @unit_worker/villager.png@ goes to @resource/resource_stone.png@.",
                "Use 1 @unit_worker/villager.png@ from @resource/sheep.png@ to build a @building_economy/mill.png@ on the @resource/berrybush.png@ (then back to @resource/sheep.png@)."
            ]
        },
        {
            "population_count": 19,
            "villager_count": 18,
            "age": 1,
            "resources": {
                "food": 7,
                "wood": 5,
                "gold": 0,
                "stone": 3
            },
            "notes": [
                "Build a @building_economy/house.png@ with the next @unit_worker/villager.png@. Send him and one extra @unit_worker/villager.png@ to @resource/resource_stone.png@.",
                "Build the @landmark_french/school-of-cavalry.png@ with the 3 @unit_worker/villager.png@ from @resource/resource_gold.png@. Research @technology_economy/wheelbarrow.png@."
            ]
        },
        {
            "population_count": 21,
            "villager_count": 20,
            "age": 1,
            "resources": {
                "food": 4,
                "wood": 5,
                "gold": 0,
                "stone": 8
            },
            "notes": [
                "Keep only 4 @unit_worker/villager.png@ on @resource/sheep.png@, send the others to @resource/resource_stone.png@.",
                "Next 2 @unit_worker/villager.png@ also go to @resource/resource_stone.png@."
            ]
        },
        {
            "population_count": 26,
            "villager_count": 25,
            "age": 2,
            "resources": {
                "food": 9,
                "wood": 5,
                "gold": 0,
                "stone": 8
            },
            "notes": [
                "Next @unit_worker/villager.png@ go to @resource/sheep.png@.",
                "With 400 @resource/resource_stone.png@, drop a @building_economy/town-center.png@ with all the @unit_worker/villager.png@ from @resource/resource_stone.png@.",
                "Build a @building_defensive/outpost.png@ with the @unit_worker/villager.png@ from @resource/resource_gold.png@."
            ]
        },
        {
            "population_count": 28,
            "villager_count": 27,
            "age": 2,
            "resources": {
                "food": 9,
                "wood": 5,
                "gold": 5,
                "stone": 0
            },
            "notes": [
                "Send next @unit_worker/villager.png@ to @resource/resource_gold.png@.",
                "Potentially add another @building_defensive/outpost.png@ (protecting second @building_economy/town-center.png@)."
            ]
        },
        {
            "population_count": -1,
            "villager_count": -1,
            "age": 2,
            "resources": {
                "food": -1,
                "wood": -1,
                "gold": -1,
                "stone": 0
            },
            "notes": [
                "Continue adding @unit_worker/villager.png@ to @resource/resource_food.png@, @resource/resource_wood.png@ and @resource/resource_gold.png@.",
                "Produce @unit_french/royal-knight-2.png@, @unit_infantry/archer-2.png@. Research @technology_defensive/arrow-slits.png@ for your @building_defensive/outpost.png@.",
                "Research @technology_economy/double-broadaxe.png@, @technology_economy/specialized-pick.png@, @technology_economy/horticulture.png@, @technology_economy/forestry.png@..."
            ]
        }
    ]
}