{
    "race": "Zerg",
    "opponent_race": "Any",
    "name": "HuShang Beginner Zerg BO (Timing Attack)",
    "patch": "4.11.0",
    "author": "Hushang",
    "source": "https://lotv.spawningtool.com/build/163886/",
    "build_order": [
        {
            "notes": [
                {
                    "supply": 13,
                    "time": "0:12",
                    "note": "@zerg_units/Overlord.png@"
                },
                {
                    "supply": 16,
                    "time": "0:48",
                    "note": "@zerg_buildings/Hatchery.png@"
                },
                {
                    "supply": 18,
                    "time": "1:10",
                    "note": "@zerg_buildings/Extractor.png@"
                },
                {
                    "supply": 17,
                    "time": "1:14",
                    "note": "@zerg_buildings/Spawning_Pool.png@"
                }
            ]
        },
        {
            "notes": [
                {
                    "supply": 20,
                    "time": "1:53",
                    "note": "@zerg_units/Overlord.png@"
                },
                {
                    "supply": 20,
                    "time": "2:01",
                    "note": "@zerg_units/Queen.png@ x2"
                },
                {
                    "supply": 20,
                    "time": "2:02",
                    "note": "@zerg_units/Zergling.png@ x4"
                },
                {
                    "supply": 32,
                    "time": "2:43",
                    "note": "@zerg_units/Overlord.png@"
                }
            ]
        },
        {
            "notes": [
                {
                    "supply": 32,
                    "time": "2:48",
                    "note": "@zerg_buildings/Lair.png@"
                },
                {
                    "supply": 36,
                    "time": "3:06",
                    "note": "@zerg_units/Overlord.png@"
                },
                {
                    "supply": 42,
                    "time": "3:14",
                    "note": "@zerg_buildings/Extractor.png@ x2"
                },
                {
                    "supply": 42,
                    "time": "3:16",
                    "note": "@zerg_buildings/Spore_Crawler.png@"
                }
            ]
        },
        {
            "notes": [
                {
                    "supply": 42,
                    "time": "3:18",
                    "note": "@zerg_buildings/Roach_Warren.png@"
                },
                {
                    "supply": 38,
                    "time": "3:26",
                    "note": "@zerg_buildings/Spore_Crawler.png@"
                },
                {
                    "supply": 47,
                    "time": "3:54",
                    "note": "@zerg_units/Overlord.png@"
                },
                {
                    "supply": 48,
                    "time": "3:55",
                    "note": "@zerg_buildings/Hatchery.png@"
                }
            ]
        },
        {
            "notes": [
                {
                    "supply": 48,
                    "time": "4:00",
                    "note": "@zerg_techs/Glial_reconstitution.png@"
                },
                {
                    "supply": 47,
                    "time": "4:15",
                    "note": "@zerg_units/Roach.png@ x7"
                },
                {
                    "supply": 59,
                    "time": "4:21",
                    "note": "@zerg_units/Roach.png@"
                },
                {
                    "supply": 59,
                    "time": "4:22",
                    "note": "@zerg_units/Overseer.png@"
                }
            ]
        },
        {
            "notes": [
                {
                    "supply": 63,
                    "time": "4:46",
                    "note": "@zerg_units/Roach.png@ x2"
                }
            ]
        }
    ]
}