{
    "civilization": "Holy Roman Empire",
    "name": "fast castle imperial",
    "author": "Beastyqt",
    "source": "https://www.youtube.com/watch?v=_yrb7ZwrDbA",
    "build_order": [{
            "population_count": 8,
            "villager_count": 6,
            "age": 1,
            "resources": {
                "food": 3,
                "wood": 0,
                "gold": 0,
                "stone": 0
            },
            "notes": [
                "Make 1 additional @unit_cavalry/scout.png@. Send 6 @unit_worker/villager.png@ on @resource/sheep.png@ (inspire  with @unit_hre/prelate.png@).",
                "Move 3 @unit_worker/villager.png@ from @resource/resource_food.png@ to @resource/resource_gold.png@ (after @unit_cavalry/scout.png@ instructions).",
                "Build @building_economy/mining-camp.png@ (2) and @building_economy/house.png@ (1) with the @unit_worker/villager.png@ from @resource/resource_gold.png@."
            ]
        },
        {
            "population_count": 13,
            "villager_count": 10,
            "age": 1,
            "resources": {
                "food": 7,
                "wood": 0,
                "gold": 3,
                "stone": 0
            },
            "notes": [
                "Send next @unit_worker/villager.png@ to @resource/sheep.png@."
            ]
        },
        {
            "population_count": 16,
            "villager_count": 13,
            "age": 1,
            "resources": {
                "food": 7,
                "wood": 3,
                "gold": 3,
                "stone": 0
            },
            "notes": [
                "Send next @unit_worker/villager.png@ to @resource/resource_wood.png@ (build @building_economy/lumber-camp.png@).",
                "Move @resource/sheep.png@ towards @landmark_hre/aachen-chapel.png@ (location: @resource/resource_food.png@>@resource/resource_wood.png@>@resource/resource_gold.png@>@resource/resource_stone.png@)."
            ]
        },
        {
            "population_count": 22,
            "villager_count": 19,
            "age": 1,
            "resources": {
                "food": 10,
                "wood": 3,
                "gold": 3,
                "stone": 0
            },
            "notes": [
                "Build @landmark_hre/aachen-chapel.png@ with 3 @unit_worker/villager.png@ from @resource/resource_food.png@, then to @resource/resource_gold.png@ (to inspire).",
                "Send next @unit_worker/villager.png@ to @resource/resource_food.png@. Build @building_economy/mill.png@, then to @resource/sheep.png@.",
                "Build a @building_economy/house.png@ with a @unit_worker/villager.png@ from @resource/resource_wood.png@. Research @technology_economy/wheelbarrow.png@."
            ]
        },
        {
            "population_count": 27,
            "villager_count": 24,
            "age": 2,
            "resources": {
                "food": 15,
                "wood": 3,
                "gold": 6,
                "stone": 0
            },
            "notes": [
                "In @age/age_2.png@, move @unit_hre/prelate.png@ in @landmark_hre/aachen-chapel.png@ and @unit_worker/villager.png@ from @landmark_hre/aachen-chapel.png@ to @resource/resource_gold.png@.",
                "Against @civilization_flag/CivIcon-EnglishAoE4_spacing.png@ / @civilization_flag/CivIcon-FrenchAoE4_spacing.png@, get more @resource/resource_wood.png@ (5) & @resource/resource_stone.png@ (1) for @building_defensive/outpost.png@ (optional).",
                "Build @building_economy/house.png@ with @unit_worker/villager.png@ from @resource/resource_wood.png@. Move @unit_worker/villager.png@ from @resource/sheep.png@ to @resource/berrybush.png@ if needed."
            ]
        },
        {
            "population_count": -1,
            "villager_count": -1,
            "age": 3,
            "resources": {
                "food": -1,
                "wood": -1,
                "gold": 0,
                "stone": 0
            },
            "notes": [
                "Build @landmark_hre/regnitz-cathedral.png@ with 9 @unit_worker/villager.png@ from @resource/resource_food.png@ (@landmark_hre/burgrave-palace.png@ if pressure), then to @resource/resource_food.png@.",
                "Make 2 @unit_hre/prelate.png@. Add 2 @unit_worker/villager.png@ to @resource/resource_wood.png@. Later, mainly on @resource/resource_food.png@, a few on @resource/resource_wood.png@.",
                "Produce military (@unit_cavalry/knight-2.png@...). Get map control. Grab relics. No @unit_worker/villager.png@ on @resource/resource_gold.png@.",
                "Prepare for @landmark_hre/palace-of-swabia.png@ (on @resource/resource_wood.png@), use @building_economy/market.png@ if needed."
            ]
        }
    ]
}