{
    "civilization": "Chinese",
    "name": "song dynasty 2 town centers",
    "author": "Beastyqt",
    "source": "https://www.youtube.com/watch?v=-Imhuc0dLIE",
    "build_order": [{
            "population_count": 9,
            "villager_count": 6,
            "age": 1,
            "resources": {
                "food": 6,
                "wood": 0,
                "gold": 0,
                "stone": 0
            },
            "notes": [
                "Make 1 @unit_cavalry/scout.png@, then 1 @unit_chinese/imperial-official.png@ (to supervise @building_economy/mill.png@).",
                "Send the first 6 @unit_worker/villager.png@ to @resource/berrybush.png@ (build @building_economy/mill.png@).",
                "Send @resource/sheep.png@ to @building_economy/mill.png@ & move @unit_worker/villager.png@ from @resource/berrybush.png@ to @resource/sheep.png@."
            ]
        },
        {
            "population_count": 10,
            "villager_count": 7,
            "age": 1,
            "resources": {
                "food": 7,
                "wood": 0,
                "gold": 0,
                "stone": 0
            },
            "notes": [
                "Buid a @building_economy/house.png@ with the next @unit_worker/villager.png@ (next to @building_economy/town-center.png@), then to @resource/sheep.png@."
            ]
        },
        {
            "population_count": 13,
            "villager_count": 10,
            "age": 1,
            "resources": {
                "food": 7,
                "wood": 0,
                "gold": 3,
                "stone": 0
            },
            "notes": [
                "Send the next 3 @unit_worker/villager.png@ to @resource/resource_gold.png@ (build @building_economy/mining-camp.png@)."
            ]
        },
        {
            "population_count": 17,
            "villager_count": 14,
            "age": 1,
            "resources": {
                "food": 7,
                "wood": 3,
                "gold": 3,
                "stone": 0
            },
            "notes": [
                "Send next @unit_worker/villager.png@ to @resource/resource_wood.png@ (straggler).",
                "At 50 @resource/resource_gold.png@ in @building_economy/mill.png@, force drop @resource/resource_food.png@ & collect tax.",
                "Build @landmark_chinese/barbican-of-the-sun.png@ with 1 @unit_worker/villager.png@ from @resource/resource_wood.png@."
            ]
        },
        {
            "population_count": 21,
            "villager_count": 18,
            "age": 1,
            "resources": {
                "food": 11,
                "wood": 3,
                "gold": 3,
                "stone": 0
            },
            "notes": [
                "Send next @unit_worker/villager.png@ to @resource/sheep.png@. Collect @resource/resource_gold.png@ with @unit_chinese/imperial-official.png@.",
                "Buid a @building_economy/house.png@ with a @unit_worker/villager.png@ from @resource/resource_wood.png@, later a @building_economy/lumber-camp.png@."
            ]
        },
        {
            "population_count": 23,
            "villager_count": 20,
            "age": 2,
            "resources": {
                "food": 8,
                "wood": 6,
                "gold": 3,
                "stone": 0
            },
            "notes": [
                "Build @landmark_chinese/imperial-academy.png@ with 3 @unit_worker/villager.png@ from @resource/resource_food.png@, then to @resource/resource_stone.png@.",
                "Next @unit_worker/villager.png@ (+ from @landmark_chinese/barbican-of-the-sun.png@) go to @resource/resource_wood.png@."
            ]
        },
        {
            "population_count": 25,
            "villager_count": 20,
            "age": 2,
            "resources": {
                "food": 4,
                "wood": 10,
                "gold": 3,
                "stone": 3
            },
            "notes": [
                "Produce 2 @unit_chinese/imperial-official.png@ (supervise @resource/resource_wood.png@, then @resource/resource_stone.png@).",
                "Move 4 @unit_worker/villager.png@ from @resource/resource_food.png@ to @resource/resource_wood.png@.",
                "The @unit_worker/villager.png@ from @landmark_chinese/imperial-academy.png@ go to @resource/resource_stone.png@ (build @building_economy/mining-camp.png@)."
            ]
        },
        {
            "population_count": 30,
            "villager_count": 25,
            "age": 2,
            "resources": {
                "food": 4,
                "wood": 10,
                "gold": 0,
                "stone": 11
            },
            "notes": [
                "Research @technology_economy/wheelbarrow.png@. Move the @unit_worker/villager.png@ from @resource/resource_gold.png@ to @resource/resource_stone.png@.",
                "Build a @building_economy/house.png@ and @building_defensive/palisade-wall.png@. Next @unit_worker/villager.png@ go to @resource/resource_stone.png@."
            ]
        },
        {
            "population_count": 36,
            "villager_count": 31,
            "age": 2,
            "resources": {
                "food": 22,
                "wood": 3,
                "gold": 6,
                "stone": 0
            },
            "notes": [
                "Build @building_economy/town-center.png@ (far from resources) with @unit_worker/villager.png@ from @resource/resource_stone.png@, then to @resource/resource_food.png@.",
                "All @unit_worker/villager.png@ from @resource/resource_wood.png@ but 3 go to @resource/resource_food.png@. Adapt @unit_chinese/imperial-official.png@ activity.",
                "Next @unit_worker/villager.png@ go to @resource/resource_gold.png@."
            ]
        },
        {
            "population_count": 49,
            "villager_count": 44,
            "age": 2,
            "resources": {
                "food": 35,
                "wood": 3,
                "gold": 6,
                "stone": 0
            },
            "notes": [
                "Next @unit_worker/villager.png@ go to @resource/resource_food.png@. Build @building_chinese/village.png@ with @unit_worker/villager.png@ from @resource/resource_gold.png@."
            ]
        },
        {
            "population_count": -1,
            "villager_count": -1,
            "age": 3,
            "resources": {
                "food": -1,
                "wood": -1,
                "gold": -1,
                "stone": -1
            },
            "notes": [
                "Build @landmark_chinese/astronomical-clocktower.png@ with 6 @unit_worker/villager.png@ from @resource/resource_food.png@.",
                "Produce military (@unit_chinese/palace-guard-3.png@, @unit_cavalry/knight-2.png@...). Build @building_religious/monastery.png@, @building_chinese/granary.png@...",
                "Re-balance economy with a lot of @resource/resource_wood.png@ for production."
            ]
        }
    ]
}