{
    "civilization": "Abbasid Dynasty",
    "name": "2 town centers",
    "author": "Beastyqt",
    "source": "https://www.youtube.com/watch?v=7kQasZLXoLM",
    "build_order": [{
            "population_count": 8,
            "villager_count": 6,
            "age": 1,
            "resources": {
                "food": 6,
                "wood": 0,
                "gold": 0,
                "stone": 0
            },
            "notes": [
                "Make a second @unit_cavalry/scout.png@.",
                "Send the first 6 @unit_worker/villager.png@ to @resource/berrybush.png@ (2 build @building_economy/mill.png@)."
            ]
        },
        {
            "population_count": 9,
            "villager_count": 7,
            "age": 1,
            "resources": {
                "food": 7,
                "wood": 0,
                "gold": 0,
                "stone": 0
            },
            "notes": [
                "Add 1 @unit_worker/villager.png@ to @resource/berrybush.png@ (split between 2 different @resource/berrybush.png@)."
            ]
        },
        {
            "population_count": 10,
            "villager_count": 8,
            "age": 1,
            "resources": {
                "food": 7,
                "wood": 0,
                "gold": 0,
                "stone": 0
            },
            "notes": [
                "Build @building_economy/house.png@ opposite to @landmark_abbasid/house-of-wisdom.png@ location.",
                "Same @unit_worker/villager.png@ builds @landmark_abbasid/house-of-wisdom.png@ (connecting resources), then to @resource/resource_gold.png@."
            ]
        },
        {
            "population_count": 13,
            "villager_count": 11,
            "age": 1,
            "resources": {
                "food": 7,
                "wood": 0,
                "gold": 4,
                "stone": 0
            },
            "notes": [
                "Following @unit_worker/villager.png@ builds @building_economy/mining-camp.png@ on @resource/resource_gold.png@.",
                "Next @unit_worker/villager.png@ go to @resource/resource_gold.png@, up to 4."
            ]
        },
        {
            "population_count": 16,
            "villager_count": 14,
            "age": 1,
            "resources": {
                "food": 4,
                "wood": 6,
                "gold": 4,
                "stone": 0
            },
            "notes": [
                "Next @unit_worker/villager.png@ go to @resource/resource_wood.png@ close to @building_economy/town-center.png@ (straggler or @resource/resource_wood.png@ line).",
                "Age up with @landmark_abbasid/economic-wing.png@, then send 3 @unit_worker/villager.png@ from @resource/resource_food.png@ to @resource/resource_wood.png@."
            ]
        },
        {
            "population_count": 18,
            "villager_count": 16,
            "age": 1,
            "resources": {
                "food": 4,
                "wood": 8,
                "gold": 4,
                "stone": 0
            },
            "notes": [
                "Continue sending @unit_worker/villager.png@ to @resource/resource_wood.png@. Build @building_economy/lumber-camp.png@ when you can."
            ]
        },
        {
            "population_count": 23,
            "villager_count": 21,
            "age": 2,
            "resources": {
                "food": 4,
                "wood": 8,
                "gold": 0,
                "stone": 9
            },
            "notes": [
                "Research @technology_economy/wheelbarrow.png@. Next @unit_worker/villager.png@ go to @resource/resource_stone.png@. Build @building_economy/house.png@ on the path, then @building_economy/mining-camp.png@.",
                "In @age/age_2.png@, research @technology_abbasid/fresh-foodstuffs.png@. Move the @unit_worker/villager.png@ from @resource/resource_gold.png@ to @resource/resource_stone.png@.",
                "Collect 75 extra @resource/resource_gold.png@ against @civilization_flag/CivIcon-FrenchAoE4_spacing.png@ (for @unit_infantry/spearman-1.png@)."
            ]
        },
        {
            "population_count": 26,
            "villager_count": 24,
            "age": 2,
            "resources": {
                "food": 7,
                "wood": 8,
                "gold": 0,
                "stone": 0
            },
            "notes": [
                "Send next @unit_worker/villager.png@ to @resource/sheep.png@. Build @building_military/barracks.png@ against @civilization_flag/CivIcon-FrenchAoE4_spacing.png@ (before @building_economy/town-center.png@).",
                "Build @building_economy/town-center.png@ (with all @unit_worker/villager.png@ from @resource/resource_stone.png@) on @resource/resource_food.png@, not forward."
            ]
        },
        {
            "population_count": 27,
            "villager_count": 25,
            "age": 2,
            "resources": {
                "food": 15,
                "wood": 9,
                "gold": 0,
                "stone": 0
            },
            "notes": [
                "Send @unit_worker/villager.png@ to @resource/resource_food.png@, up to 15.",
                "Build @building_military/barracks.png@/@building_military/archery-range.png@/@building_military/stable.png@ (adapt). Produce units."
            ]
        },
        {
            "population_count": -1,
            "villager_count": -1,
            "age": 2,
            "resources": {
                "food": -1,
                "wood": -1,
                "gold": -1,
                "stone": -1
            },
            "notes": [
                "Send @unit_worker/villager.png@ to @resource/resource_gold.png@ (up to 3) and to @resource/resource_wood.png@ (up to 22).",
                "Continue military production (buildings & units), use @unit_abbasid/camel-archer-2.png@ aura.",
                "Build @building_technology/blacksmith.png@. Connect 2 @building_economy/town-center.png@. Put more @unit_worker/villager.png@ on @resource/resource_food.png@ & @resource/resource_gold.png@ for @age/age_3.png@."
            ]
        }
    ]
}