{
    "civilization": "English",
    "name": "spearmen longbows",
    "author": "Beastyqt",
    "source": "https://www.youtube.com/watch?v=yWllEP7uE0A",
    "build_order": [{
            "population_count": 9,
            "villager_count": 7,
            "age": 1,
            "resources": {
                "food": 2,
                "wood": 2,
                "gold": 2,
                "stone": 0
            },
            "notes": [
                "Split the first 6 @unit_worker/villager.png@ between @resource/resource_food.png@ (2) @resource/resource_wood.png@ (2) and @resource/resource_gold.png@ (2).",
                "Make an additional @unit_cavalry/scout.png@.",
                "Build a @building_economy/house.png@, then a @building_economy/mill.png@ (behind @building_economy/town-center.png@) with the next @unit_worker/villager.png@."
            ]
        },
        {
            "population_count": 18,
            "villager_count": 16,
            "age": 1,
            "resources": {
                "food": 12,
                "wood": 2,
                "gold": 2,
                "stone": 0
            },
            "notes": [
                "Next @unit_worker/villager.png@ (and the one building the @building_economy/mill.png@) go to @resource/resource_food.png@. Research @technology_economy/wheelbarrow.png@.",
                "New @unit_worker/villager.png@ (or from @resource/sheep.png@) go to @building_economy/farm.png@ each time you have 37 @resource/resource_wood.png@.",
                "Harass enemy @unit_worker/villager.png@ with the 2 @unit_cavalry/scout.png@ (do not loose them)."
            ]
        },
        {
            "population_count": 20,
            "villager_count": 18,
            "age": 1,
            "resources": {
                "food": 4,
                "wood": 9,
                "gold": 2,
                "stone": 0
            },
            "notes": [
                "Build the @landmark_english/council-hall.png@ with 3 @unit_worker/villager.png@ from @resource/sheep.png@. Build a @building_economy/house.png@.",
                "Send all but 4 @unit_worker/villager.png@ from @resource/resource_food.png@ (keep @building_economy/farm.png@) to @resource/resource_wood.png@."
            ]
        },
        {
            "population_count": 24,
            "villager_count": 22,
            "age": 1,
            "resources": {
                "food": 8,
                "wood": 8,
                "gold": 2,
                "stone": 0
            },
            "notes": [
                "Continue rallying new @unit_worker/villager.png@ to @resource/resource_wood.png@.",
                "Build additional @building_economy/farm.png@ with the @unit_worker/villager.png@ from @resource/resource_wood.png@.",
                "Build a @building_military/barracks.png@ when at 75% of @age/age_2.png@."
            ]
        },
        {
            "population_count": 43,
            "villager_count": 28,
            "age": 2,
            "resources": {
                "food": 10,
                "wood": 15,
                "gold": 2,
                "stone": 0
            },
            "notes": [
                "Once in @age/age_2.png@, research @technology_economy/double-broadaxe.png@. Train @unit_english/longbowman-2.png@ and @unit_infantry/spearman-1.png@.",
                "The @unit_worker/villager.png@ from @landmark_english/council-hall.png@ and the next ones go to @resource/resource_wood.png@.",
                "Add additional @building_economy/farm.png@ (up to 10). Build an aggressive @building_defensive/outpost.png@."
            ]
        },
        {
            "population_count": -1,
            "villager_count": -1,
            "age": 2,
            "resources": {
                "food": -1,
                "wood": -1,
                "gold": 2,
                "stone": 0
            },
            "notes": [
                "Build a @building_technology/blacksmith.png@. Research @technology_military/steeled-arrow.png@.",
                "Rally new @unit_worker/villager.png@ to @resource/resource_wood.png@, build some additional @building_economy/farm.png@.",
                "Put pressure with @unit_english/longbowman-2.png@ and @unit_infantry/spearman-1.png@ (potentially @unit_siege/battering-ram.png@ later)."
            ]
        }
    ]
}