{
    "name": "all in scouts",
    "author": "Hera",
    "source": "https://discord.com/invite/RdnZdZRkCq (Hera Discord)",
    "build_order": [{
            "villager_count": 6,
            "age": 1,
            "resources": {
                "wood": 0,
                "food": {
                    "Sheep":6
                },
                "gold": 0,
                "stone": 0
            },
            "notes": [
                "Build 2 @other/House_aoe2DE.png@.",
                "Send the fitst 6 @resource/MaleVillDE.jpg@ to @animal/Sheep_aoe2DE.png@."
            ]
        },
        {
            "villager_count": 9,
            "age": 1,
            "resources": {
                "wood": 3,
                "food": {
                    "Sheep":6
                },
                "gold": 0,
                "stone": 0
            },
            "notes": [
                "Build the first @lumber_camp/Lumber_camp_aoe2de.png@.",
                "Send the next 3 @resource/MaleVillDE.jpg@ to @resource/Aoe2de_wood.png@."
            ]
        },
        {
            "villager_count": 10,
            "age": 1,
            "resources": {
                "wood": 3,
                "food": {
                    "Boar":7
                },
                "gold": 0,
                "stone": 0
            },
            "notes": [
                "Lure the first @animal/Boar_aoe2DE.png@."
            ]
        },
        {
            "villager_count": 11,
            "age": 1,
            "resources": {
                "wood": 3,
                "food": {
                    "Boar":8
                },
                "gold": 0,
                "stone": 0
            },
            "notes": [
                "Next @resource/MaleVillDE.jpg@ go to @resource/Aoe2de_food.png@ under @town_center/Towncenter_aoe2DE.png@."
            ]
        },
        {
            "villager_count": 12,
            "age": 1,
            "resources": {
                "wood": 3,
                "food": {
                    "Boar":8,
					"Berries":1
                },
                "gold": 0,
                "stone": 0
            },
            "notes": [
                "Build a @other/House_aoe2DE.png@.",
                "Build a @mill/Mill_aoe2de.png@ and gather @resource/BerryBushDE.png@."
            ]
        },
        {
            "villager_count": 14,
            "age": 1,
            "resources": {
                "wood": 3,
                "food": {
                    "Boar":8,
					"Berries":3
                },
                "gold": 0,
                "stone": 0
            },
            "notes": [
                "Send 2 @resource/MaleVillDE.jpg@ to @resource/BerryBushDE.png@."
            ]
        },
        {
            "villager_count": 15,
            "age": 1,
            "resources": {
                "wood": 3,
                "food": {
                    "Boar":9,
					"Berries":3
                },
                "gold": 0,
                "stone": 0
            },
            "notes": [
                "Lure the second @animal/Boar_aoe2DE.png@."
            ]
        },
        {
            "villager_count": 16,
            "age": 1,
            "resources": {
                "wood": 3,
                "food": {
                    "Boar":9,
					"Berries":4
                },
                "gold": 0,
                "stone": 0
            },
            "notes": [
                "Add 1 @resource/MaleVillDE.jpg@ to @resource/BerryBushDE.png@."
            ]
        },
        {
            "villager_count": 17,
            "age": 1,
            "resources": {
                "wood": 3,
                "food": {
                    "Boar":10,
					"Berries":4
                },
                "gold": 0,
                "stone": 0
            },
            "notes": [
                "Add 1 @resource/MaleVillDE.jpg@ to @resource/Aoe2de_food.png@ under @town_center/Towncenter_aoe2DE.png@."
            ]
        },
        {
            "villager_count": 19,
            "age": 1,
            "resources": {
                "wood": 5,
                "food": {
                    "Boar":10,
					"Berries":4
                },
                "gold": 0,
                "stone": 0
            },
            "notes": [
                "Add 2 @resource/MaleVillDE.jpg@ to @resource/Aoe2de_wood.png@."
            ]
        },
        {
            "villager_count": 20,
            "age": 1,
            "resources": {
                "wood": 6,
                "food": {
                    "Boar":10,
					"Berries":4
                },
                "gold": 0,
                "stone": 0
            },
            "notes": [
                "Build a second @lumber_camp/Lumber_camp_aoe2de.png@.",
                "Add 1 @resource/MaleVillDE.jpg@ to @resource/Aoe2de_wood.png@."
            ]
        },
        {
            "villager_count": 20,
            "age": 2,
            "resources": {
                "wood": 9,
                "food": {
                    "Boar":7,
					"Berries":4
                },
                "gold": 0,
                "stone": 0
            },
            "notes": [
                "Research @town_center/LoomDE.png@, then click up to @age/FeudalAgeIconDE.png@.",
                "Send 3 @resource/MaleVillDE.jpg@ from @town_center/Towncenter_aoe2DE.png@ to @lumber_camp/Lumber_camp_aoe2de.png@.",
                "Build @barracks/Barracks_aoe2DE.png@ at 60% up."
            ]
        },
        {
            "villager_count": 21,
            "age": 2,
            "resources": {
                "wood": 9,
                "food": 11,
                "gold": 1,
                "stone": 0
            },
            "notes": [
                "Build a @stable/Stable_aoe2DE.png@ and make @stable/Scoutcavalry_aoe2DE.png@.",
                "Research @lumber_camp/DoubleBitAxe_aoe2DE.png@ and @mill/HorseCollarDE.png@. Make more @mill/FarmDE.png@.",
                "Long distance @mining_camp/Mining_camp_aoe2de.png@ with next @resource/MaleVillDE.jpg@ to get 100 @resource/Aoe2de_gold.png@."
            ]
        },
        {
            "villager_count": 28,
            "age": 2,
            "resources": {
                "wood": 9,
                "food": 18,
                "gold": 1,
                "stone": 0
            },
            "notes": [
                "Research @town_center/WheelbarrowDE.png@ (around 14 @mill/FarmDE.png@)."
            ]
        },
        {
            "villager_count": -1,
            "age": 2,
            "resources": {
                "wood": -1,
                "food": -1,
                "gold": -1,
                "stone": -1
            },
            "notes": [
                "Research @stable/BloodlinesDE.png@ with the 100 @resource/Aoe2de_gold.png@. Send the @resource/MaleVillDE.jpg@ from @mining_camp/Mining_camp_aoe2de.png@ to @mill/FarmDE.png@.",
                "Send @resource/MaleVillDE.jpg@ from @resource/BerryBushDE.png@ to @mill/FarmDE.png@ (when depleted).",
                "Build a second @stable/Stable_aoe2DE.png@ and a @blacksmith/Blacksmith_aoe2de.png@. Research @blacksmith/ScaleBardingArmorDE.png@ and @blacksmith/Forging_aoe2de.png@.",
                "Keep making @mill/FarmDE.png@ (second @mill/Mill_aoe2de.png@ if needed) and send @resource/MaleVillDE.jpg@ to @resource/Aoe2de_wood.png@.",
                "Make a @stable/Stable_aoe2DE.png@ for each additional 6-7 @mill/FarmDE.png@."
            ]
        }
    ]
}