{
    "name": "bohemians drush fc cannoneers",
    "civilization": "Bohemians",
    "author": "Hera",
    "source": "https://discord.com/invite/RdnZdZRkCq (Hera Discord)",
    "build_order": [{
            "villager_count": 6,
            "age": 1,
            "resources": {
                "wood": 0,
                "food": 6,
                "gold": 0,
                "stone": 0
            },
            "notes": [
                "Build 2 @other/House_aoe2DE.png@.",
                "Send the first 6 @resource/MaleVillDE.jpg@ to @animal/Sheep_aoe2DE.png@."
            ]
        },
        {
            "villager_count": 10,
            "age": 1,
            "resources": {
                "wood": 4,
                "food": 6,
                "gold": 0,
                "stone": 0
            },
            "notes": [
                "Build the first @lumber_camp/Lumber_camp_aoe2de.png@.",
                "Send the next 4 @resource/MaleVillDE.jpg@ to @resource/Aoe2de_wood.png@."
            ]
        },
        {
            "villager_count": 11,
            "age": 1,
            "resources": {
                "wood": 4,
                "food": 7,
                "gold": 0,
                "stone": 0
            },
            "notes": [
                "Lure the first @animal/Boar_aoe2DE.png@."
            ]
        },
        {
            "villager_count": 12,
            "age": 1,
            "resources": {
                "wood": 4,
                "food": 8,
                "gold": 0,
                "stone": 0
            },
            "notes": [
                "Build a @other/House_aoe2DE.png@.",
                "Build a @mill/Mill_aoe2de.png@ and gather @resource/BerryBushDE.png@."
            ]
        },
        {
            "villager_count": 14,
            "age": 1,
            "resources": {
                "wood": 4,
                "food": 10,
                "gold": 0,
                "stone": 0
            },
            "notes": [
                "Send 2 @resource/MaleVillDE.jpg@ to @resource/BerryBushDE.png@."
            ]
        },
        {
            "villager_count": 15,
            "age": 1,
            "resources": {
                "wood": 4,
                "food": 11,
                "gold": 0,
                "stone": 0
            },
            "notes": [
                "Lure the second @animal/Boar_aoe2DE.png@."
            ]
        },
        {
            "villager_count": 16,
            "age": 1,
            "resources": {
                "wood": 4,
                "food": 12,
                "gold": 0,
                "stone": 0
            },
            "notes": [
                "Add 1 @resource/MaleVillDE.jpg@ to @resource/BerryBushDE.png@."
            ]
        },
        {
            "villager_count": 17,
            "age": 1,
            "resources": {
                "wood": 4,
                "food": 12,
                "gold": 0,
                "stone": 0
            },
            "notes": [
                "Next @resource/MaleVillDE.jpg@ builds a @other/House_aoe2DE.png@, then a @barracks/Barracks_aoe2DE.png@, then another @other/House_aoe2DE.png@.",
                "Once done, this @resource/MaleVillDE.jpg@ starts the @defensive_structures/Palisade_wall_aoe2de.png@."
            ]
        },
        {
            "villager_count": 20,
            "age": 1,
            "resources": {
                "wood": 4,
                "food": 15,
                "gold": 0,
                "stone": 0
            },
            "notes": [
                "Make 3 @barracks/MilitiaDE.png@ and send them forward with the @stable/Scoutcavalry_aoe2DE.png@.",
                "Next 3 @resource/MaleVillDE.jpg@ go to @resource/Aoe2de_food.png@ under @town_center/Towncenter_aoe2DE.png@."
            ]
        },
        {
            "villager_count": 21,
            "age": 1,
            "resources": {
                "wood": 4,
                "food": 15,
                "gold": 1,
                "stone": 0
            },
            "notes": [
                "Next @resource/MaleVillDE.jpg@ mines 10 @resource/Aoe2de_gold.png@ without building @mining_camp/Mining_camp_aoe2de.png@.",
                "Once done, send this @resource/MaleVillDE.jpg@ to @resource/Aoe2de_food.png@ under @town_center/Towncenter_aoe2DE.png@."
            ]
        },
        {
            "villager_count": 22,
            "age": 1,
            "resources": {
                "wood": 4,
                "food": 16,
                "gold": 0,
                "stone": 0
            },
            "notes": [
                "Add 1 @resource/MaleVillDE.jpg@ to @defensive_structures/Palisade_wall_aoe2de.png@ (for full wall)."
            ]
        },
        {
            "villager_count": 25,
            "age": 1,
            "resources": {
                "wood": 7,
                "food": 16,
                "gold": 0,
                "stone": 0
            },
            "notes": [
                "Next 3 @resource/MaleVillDE.jpg@ go to @resource/Aoe2de_wood.png@."
            ]
        },
        {
            "villager_count": 27,
            "age": 1,
            "resources": {
                "wood": 10,
                "food": 13,
                "gold": 4,
                "stone": 0
            },
            "notes": [
                "Build a @mining_camp/Mining_camp_aoe2de.png@. Add 2 @resource/MaleVillDE.jpg@ to @resource/Aoe2de_gold.png@.",
                "Seed @mill/FarmDE.png@ when @animal/Sheep_aoe2DE.png@ are depleted. Keep 3 @resource/MaleVillDE.jpg@ on @resource/Aoe2de_wood.png@ (straggler).",
                "Once full @defensive_structures/Palisade_wall_aoe2de.png@ is done, send the 2 @resource/MaleVillDE.jpg@ to @resource/Aoe2de_gold.png@ (maybe after @age/FeudalAgeIconDE.png@)."
            ]
        },
        {
            "villager_count": 27,
            "age": 2,
            "resources": {
                "wood": 10,
                "food": 13,
                "gold": 4,
                "stone": 0
            },
            "notes": [
                "Research @town_center/LoomDE.png@, then click up to @age/FeudalAgeIconDE.png@.",
                "Keep harassing with @barracks/MilitiaDE.png@ and @stable/Scoutcavalry_aoe2DE.png@."
            ]
        },
        {
            "villager_count": 29,
            "age": 2,
            "resources": {
                "wood": 7,
                "food": 13,
                "gold": 6,
                "stone": 0
            },
            "notes": [
                "Build 1 @archery_range/Archery_range_aoe2DE.png@ and 1 @blacksmith/Blacksmith_aoe2de.png@ with the 3 @resource/MaleVillDE.jpg@ on @resource/Aoe2de_wood.png@ (straggler).",
                "Send next 2 @resource/MaleVillDE.jpg@ to @resource/Aoe2de_gold.png@."
            ]
        },
        {
            "villager_count": 29,
            "age": 3,
            "resources": {
                "wood": 7,
                "food": 16,
                "gold": 6,
                "stone": 0
            },
            "notes": [
                "Click up to @age/CastleAgeIconDE.png@.",
                "Research @mill/HorseCollarDE.png@, @lumber_camp/DoubleBitAxe_aoe2DE.png@ and (later) @blacksmith/PaddedArcherArmorDE.png@.",
                "After @mill/HorseCollarDE.png@, build 3 @mill/FarmDE.png@ with the builder @resource/MaleVillDE.jpg@."
            ]
        },
        {
            "villager_count": -1,
            "age": 3,
            "resources": {
                "wood": -1,
                "food": -1,
                "gold": -1,
                "stone": -1
            },
            "notes": [
                "Continue producing @resource/MaleVillDE.jpg@ for @resource/Aoe2de_gold.png@/@resource/Aoe2de_wood.png@/@mill/FarmDE.png@.",
                "Build @university/University_AoE2_DE.png@ and 2 @archery_range/Archery_range_aoe2DE.png@. Research @university/ChemistryDE.png@, @lumber_camp/BowSawDE.png@ and @blacksmith/LeatherArcherArmorDE.png@.",
                "After @university/ChemistryDE.png@, produce @archery_range/Hand_cannoneer_aoe2DE.png@ non stop to put pressure.",
                "Build @siege_workshop/Siege_workshop_aoe2DE.png@ for @siege_workshop/Mangonel_aoe2DE.png@/@siege_workshop/Scorpion_aoe2DE.png@. Build @monastery/MonasteryAoe2DE.png@ for @monastery/Monk_aoe2DE.png@ and @monastery/FervorDE.png@."
            ]
        }
    ]
}