{
    "name": "britons 20 pop archers",
    "civilization": "Britons",
    "author": "Hera",
    "source": "https://discord.com/invite/RdnZdZRkCq (Hera Discord)",
    "build_order": [{
            "villager_count": 5,
            "age": 1,
            "resources": {
                "wood": 0,
                "food": 5,
                "gold": 0,
                "stone": 0
            },
            "notes": [
                "Build 2 @other/House_aoe2DE.png@.",
                "Send the first 5 @resource/MaleVillDE.jpg@ to @animal/Sheep_aoe2DE.png@."
            ]
        },
        {
            "villager_count": 8,
            "age": 1,
            "resources": {
                "wood": 3,
                "food": 5,
                "gold": 0,
                "stone": 0
            },
            "notes": [
                "Build the first @lumber_camp/Lumber_camp_aoe2de.png@.",
                "Send the next 3 @resource/MaleVillDE.jpg@ to @resource/Aoe2de_wood.png@."
            ]
        },
        {
            "villager_count": 9,
            "age": 1,
            "resources": {
                "wood": 3,
                "food": 6,
                "gold": 0,
                "stone": 0
            },
            "notes": [
                "Lure the first @animal/Boar_aoe2DE.png@."
            ]
        },
        {
            "villager_count": 10,
            "age": 1,
            "resources": {
                "wood": 3,
                "food": 7,
                "gold": 0,
                "stone": 0
            },
            "notes": [
                "Add 1 @resource/MaleVillDE.jpg@ to @resource/Aoe2de_food.png@ under @town_center/Towncenter_aoe2DE.png@."
            ]
        },
        {
            "villager_count": 11,
            "age": 1,
            "resources": {
                "wood": 3,
                "food": 8,
                "gold": 0,
                "stone": 0
            },
            "notes": [
                "Build a @other/House_aoe2DE.png@.",
                "Build a @mill/Mill_aoe2de.png@ and gather @resource/BerryBushDE.png@."
            ]
        },
        {
            "villager_count": 13,
            "age": 1,
            "resources": {
                "wood": 3,
                "food": 10,
                "gold": 0,
                "stone": 0
            },
            "notes": [
                "Send 2 @resource/MaleVillDE.jpg@ to @resource/BerryBushDE.png@."
            ]
        },
        {
            "villager_count": 14,
            "age": 1,
            "resources": {
                "wood": 3,
                "food": 11,
                "gold": 0,
                "stone": 0
            },
            "notes": [
                "Lure the second @animal/Boar_aoe2DE.png@."
            ]
        },
        {
            "villager_count": 15,
            "age": 1,
            "resources": {
                "wood": 3,
                "food": 12,
                "gold": 0,
                "stone": 0
            },
            "notes": [
                "Add 1 @resource/MaleVillDE.jpg@ to @resource/BerryBushDE.png@."
            ]
        },
        {
            "villager_count": 19,
            "age": 1,
            "resources": {
                "wood": 3,
                "food": 16,
                "gold": 0,
                "stone": 0
            },
            "notes": [
                "Add 4 @resource/MaleVillDE.jpg@ to @resource/Aoe2de_food.png@ under @town_center/Towncenter_aoe2DE.png@."
            ]
        },
        {
            "villager_count": 19,
            "age": 2,
            "resources": {
                "wood": 10,
                "food": 5,
                "gold": 2,
                "stone": 0
            },
            "notes": [
                "Research @town_center/LoomDE.png@, then click up to @age/FeudalAgeIconDE.png@.",
                "Send 7 @resource/MaleVillDE.jpg@ from @town_center/Towncenter_aoe2DE.png@ to first (2) and second (5) @lumber_camp/Lumber_camp_aoe2de.png@.",
                "Send 2 @resource/MaleVillDE.jpg@ from @town_center/Towncenter_aoe2DE.png@ to @resource/Aoe2de_gold.png@ (build  @mining_camp/Mining_camp_aoe2de.png@).",
                "Send 2 @resource/MaleVillDE.jpg@ from @town_center/Towncenter_aoe2DE.png@ to build @barracks/Barracks_aoe2DE.png@ and @other/House_aoe2DE.png@."
            ]
        },
        {
            "villager_count": 22,
            "age": 2,
            "resources": {
                "wood": 10,
                "food": 5,
                "gold": 5,
                "stone": 0
            },
            "notes": [
                "Build 1 @archery_range/Archery_range_aoe2DE.png@ (with 2 @resource/MaleVillDE.jpg@) and make @archery_range/Archer_aoe2DE.png@. Research @lumber_camp/DoubleBitAxe_aoe2DE.png@.",
                "Build @defensive_structures/Palisade_wall_aoe2de.png@ & @other/House_aoe2DE.png@ with 2 building @resource/MaleVillDE.jpg@ (different places).",
                "Send the next 3 @resource/MaleVillDE.jpg@ to @resource/Aoe2de_gold.png@.",
                "Send 1 @resource/MaleVillDE.jpg@ from @animal/Sheep_aoe2DE.png@ to @resource/Aoe2de_wood.png@ (straggler), then seed @mill/FarmDE.png@.",
                "Build a @blacksmith/Blacksmith_aoe2de.png@ with 1 of the walling @resource/MaleVillDE.jpg@. Research @blacksmith/FletchingDE.png@."
            ]
        },
        {
            "villager_count": 35,
            "age": 2,
            "resources": {
                "wood": 10,
                "food": 16,
                "gold": 9,
                "stone": 0
            },
            "notes": [
                "Seed @mill/FarmDE.png@ with new and walling @resource/MaleVillDE.jpg@.",
                "When @resource/BerryBushDE.png@ are depleted, send the 4 @resource/MaleVillDE.jpg@ to @resource/Aoe2de_gold.png@.",
                "Move with 1-2 @barracks/Spearman_aoe2DE.png@ and 3-4 @archery_range/Archer_aoe2DE.png@ WITH @blacksmith/FletchingDE.png@ !!!",
                "Continue massing @archery_range/Archer_aoe2DE.png@ from 1 @archery_range/Archery_range_aoe2DE.png@."
            ]
        },
        {
            "villager_count": 35,
            "age": 3,
            "resources": {
                "wood": 10,
                "food": 16,
                "gold": 9,
                "stone": 0
            },
            "notes": [
                "Build the second @archery_range/Archery_range_aoe2DE.png@. Click up to @age/CastleAgeIconDE.png@ (@resource/MaleVillDE.jpg@ to @resource/Aoe2de_food.png@ otherwise).",
                "Research @mill/HorseCollarDE.png@, @mining_camp/GoldMiningDE.png@, @blacksmith/PaddedArcherArmorDE.png@. Continue massing @archery_range/Archer_aoe2DE.png@.",
                "In 1v1, add 1 @stable/Stable_aoe2DE.png@ (for @stable/Knight_aoe2DE.png@ against @archery_range/Skirmisher_aoe2DE.png@)."
            ]
        },
        {
            "villager_count": -1,
            "age": 3,
            "resources": {
                "wood": -1,
                "food": -1,
                "gold": -1,
                "stone": -1
            },
            "notes": [
                "Research @archery_range/ArbalestDE.png@, @blacksmith/BodkinArrowDE.png@ and @lumber_camp/BowSawDE.png@.",
                "Drop 2 @town_center/Towncenter_aoe2DE.png@ (@resource/Aoe2de_wood.png@ and @resource/Aoe2de_gold.png@). Build @university/University_AoE2_DE.png@, research @university/BallisticsDE.png@.",
                "Force fights and pick off @resource/MaleVillDE.jpg@ with @archery_range/Crossbowman_aoe2DE.png@."
            ]
        }
    ]
}