{
    "name": "burgundians scouts cavaliers",
    "civilization": "Burgundians",
    "author": "Hera",
    "source": "https://discord.com/invite/RdnZdZRkCq (Hera Discord)",
    "build_order": [{
            "villager_count": 6,
            "age": 1,
            "resources": {
                "wood": 0,
                "food": 6,
                "gold": 0,
                "stone": 0
            },
            "notes": [
                "Build 2 @other/House_aoe2DE.png@.",
                "Send the fitst 6 @resource/MaleVillDE.jpg@ to @animal/Sheep_aoe2DE.png@."
            ]
        },
        {
            "villager_count": 9,
            "age": 1,
            "resources": {
                "wood": 3,
                "food": 6,
                "gold": 0,
                "stone": 0
            },
            "notes": [
                "Build the first @lumber_camp/Lumber_camp_aoe2de.png@.",
                "Send the next 3 @resource/MaleVillDE.jpg@ to @resource/Aoe2de_wood.png@."
            ]
        },
        {
            "villager_count": 10,
            "age": 1,
            "resources": {
                "wood": 3,
                "food": 7,
                "gold": 0,
                "stone": 0
            },
            "notes": [
                "Lure the first @animal/Boar_aoe2DE.png@."
            ]
        },
        {
            "villager_count": 13,
            "age": 1,
            "resources": {
                "wood": 3,
                "food": 10,
                "gold": 0,
                "stone": 0
            },
            "notes": [
                "Build a @other/House_aoe2DE.png@.",
                "Build a @mill/Mill_aoe2de.png@ and send 3 @resource/MaleVillDE.jpg@ to @resource/BerryBushDE.png@."
            ]
        },
        {
            "villager_count": 14,
            "age": 1,
            "resources": {
                "wood": 3,
                "food": 11,
                "gold": 0,
                "stone": 0
            },
            "notes": [
                "Lure the second @animal/Boar_aoe2DE.png@."
            ]
        },
        {
            "villager_count": 15,
            "age": 1,
            "resources": {
                "wood": 3,
                "food": 12,
                "gold": 0,
                "stone": 0
            },
            "notes": [
                "Add 1 @resource/MaleVillDE.jpg@ to @resource/BerryBushDE.png@. Research @lumber_camp/DoubleBitAxe_aoe2DE.png@."
            ]
        },
        {
            "villager_count": 16,
            "age": 1,
            "resources": {
                "wood": 3,
                "food": 13,
                "gold": 0,
                "stone": 0
            },
            "notes": [
                "Next @resource/MaleVillDE.jpg@ goes to @resource/Aoe2de_food.png@ under @town_center/Towncenter_aoe2DE.png@."
            ]
        },
        {
            "villager_count": 17,
            "age": 1,
            "resources": {
                "wood": 3,
                "food": 13,
                "gold": 0,
                "stone": 0
            },
            "notes": [
                "Next @resource/MaleVillDE.jpg@ builds a @other/House_aoe2DE.png@ and starts the @defensive_structures/Palisade_wall_aoe2de.png@."
            ]
        },
        {
            "villager_count": 18,
            "age": 1,
            "resources": {
                "wood": 3,
                "food": 14,
                "gold": 0,
                "stone": 0
            },
            "notes": [
                "Add 1 @resource/MaleVillDE.jpg@ to @resource/Aoe2de_food.png@ under @town_center/Towncenter_aoe2DE.png@."
            ]
        },
        {
            "villager_count": 20,
            "age": 1,
            "resources": {
                "wood": 5,
                "food": 14,
                "gold": 0,
                "stone": 0
            },
            "notes": [
                "Add 2 @resource/MaleVillDE.jpg@ to @resource/Aoe2de_wood.png@."
            ]
        },
        {
            "villager_count": 20,
            "age": 2,
            "resources": {
                "wood": 9,
                "food": 10,
                "gold": 0,
                "stone": 0
            },
            "notes": [
                "Research @town_center/LoomDE.png@, then click up to @age/FeudalAgeIconDE.png@.",
                "Send 4 @resource/MaleVillDE.jpg@ from @town_center/Towncenter_aoe2DE.png@ to build second @lumber_camp/Lumber_camp_aoe2de.png@.",
                "Research @mill/HorseCollarDE.png@. Build @barracks/Barracks_aoe2DE.png@ and @other/House_aoe2DE.png@ (with @resource/MaleVillDE.jpg@ from @defensive_structures/Palisade_wall_aoe2de.png@)."
            ]
        },
        {
            "villager_count": 29,
            "age": 2,
            "resources": {
                "wood": 9,
                "food": 18,
                "gold": 0,
                "stone": 0
            },
            "notes": [
                "Build a @stable/Stable_aoe2DE.png@ (with 1 @resource/MaleVillDE.jpg@ from @defensive_structures/Palisade_wall_aoe2de.png@ and 1 from @town_center/Towncenter_aoe2DE.png@).",
                "Continue @defensive_structures/Palisade_wall_aoe2de.png@ and @other/House_aoe2DE.png@ with these @resource/MaleVillDE.jpg@. Research @lumber_camp/BowSawDE.png@.",
                "Seed @mill/FarmDE.png@ (up to 14), send to @resource/Aoe2de_wood.png@ (straggler) if needed.",
                "Produce @stable/Scoutcavalry_aoe2DE.png@ to defend/attack."
            ]
        },
        {
            "villager_count": 34,
            "age": 2,
            "resources": {
                "wood": 9,
                "food": 18,
                "gold": 7,
                "stone": 0
            },
            "notes": [
                "Send the next 5 @resource/MaleVillDE.jpg@ to @resource/Aoe2de_gold.png@.",
                "Add the 2 @resource/MaleVillDE.jpg@ from @defensive_structures/Palisade_wall_aoe2de.png@ (once done) to @resource/Aoe2de_gold.png@.",
                "Research @town_center/WheelbarrowDE.png@. Build a @blacksmith/Blacksmith_aoe2de.png@.",
                "When depleted, send @resource/MaleVillDE.jpg@ from @resource/BerryBushDE.png@ to @mill/FarmDE.png@."
            ]
        },
        {
            "villager_count": 34,
            "age": 3,
            "resources": {
                "wood": 9,
                "food": 18,
                "gold": 7,
                "stone": 0
            },
            "notes": [
                "Click up to @age/CastleAgeIconDE.png@. Research @mill/HeavyPlowDE.png@, @blacksmith/ScaleBardingArmorDE.png@ and @blacksmith/Forging_aoe2de.png@.",
                "Build a second @stable/Stable_aoe2DE.png@. Research @mining_camp/GoldMiningDE.png@."
            ]
        },
        {
            "villager_count": -1,
            "age": 3,
            "resources": {
                "wood": -1,
                "food": -1,
                "gold": -1,
                "stone": 0
            },
            "notes": [
                "Research @stable/Cavalier-research.jpg@ and @blacksmith/ChainBardingDE.png@ (no upgrade from @age/ImperialAgeIconDE.png@).",
                "Prodcude @stable/Cavalier_aoe2DE.png@ from both @stable/Stable_aoe2DE.png@.",
                "Go all in with @monastery/Monk_aoe2DE.png@ & @siege_workshop/Siege_workshop_aoe2DE.png@ OR drop 2 @town_center/Towncenter_aoe2DE.png@."
            ]
        }
    ]
}