{
    "name": "chinese scouts into archers",
    "civilization": "Chinese",
    "author": "Hera",
    "source": "https://discord.com/invite/RdnZdZRkCq (Hera Discord)",
    "build_order": [{
            "villager_count": 7,
            "age": 1,
            "resources": {
                "wood": 0,
                "food": 7,
                "gold": 0,
                "stone": 0
            },
            "notes": [
                "All 6 @resource/MaleVillDE.jpg@ go to @animal/Sheep_aoe2DE.png@. Next @resource/MaleVillDE.jpg@ builds 1 @other/House_aoe2DE.png@ (then @animal/Sheep_aoe2DE.png@).",
                "Research @town_center/LoomDE.png@, force drop @resource/Aoe2de_food.png@ when @animal/Sheep_aoe2DE.png@ has 40 @resource/Aoe2de_food.png@."
            ]
        },
        {
            "villager_count": 10,
            "age": 1,
            "resources": {
                "wood": 3,
                "food": 7,
                "gold": 0,
                "stone": 0
            },
            "notes": [
                "Build the first @lumber_camp/Lumber_camp_aoe2de.png@. Send the next 3 @resource/MaleVillDE.jpg@ to @resource/Aoe2de_wood.png@.",
                "Use 1 @resource/MaleVillDE.jpg@ from @animal/Sheep_aoe2DE.png@ to lure the first @animal/Boar_aoe2DE.png@."
            ]
        },
        {
            "villager_count": 11,
            "age": 1,
            "resources": {
                "wood": 3,
                "food": 8,
                "gold": 0,
                "stone": 0
            },
            "notes": [
                "Build a @other/House_aoe2DE.png@.",
                "Build a @mill/Mill_aoe2de.png@ and gather @resource/BerryBushDE.png@."
            ]
        },
        {
            "villager_count": 13,
            "age": 1,
            "resources": {
                "wood": 3,
                "food": 10,
                "gold": 0,
                "stone": 0
            },
            "notes": [
                "Send 2 @resource/MaleVillDE.jpg@ to @resource/BerryBushDE.png@."
            ]
        },
        {
            "villager_count": 14,
            "age": 1,
            "resources": {
                "wood": 3,
                "food": 11,
                "gold": 0,
                "stone": 0
            },
            "notes": [
                "Lure the second @animal/Boar_aoe2DE.png@. Luring 1-2 @animal/Deer_aoe2DE.png@ can help."
            ]
        },
        {
            "villager_count": 15,
            "age": 1,
            "resources": {
                "wood": 3,
                "food": 12,
                "gold": 0,
                "stone": 0
            },
            "notes": [
                "Next @resource/MaleVillDE.jpg@ builds @other/House_aoe2DE.png@, then goes to @resource/BerryBushDE.png@."
            ]
        },
        {
            "villager_count": 19,
            "age": 1,
            "resources": {
                "wood": 3,
                "food": 16,
                "gold": 0,
                "stone": 0
            },
            "notes": [
                "Add 4 @resource/MaleVillDE.jpg@ to @resource/Aoe2de_food.png@ under @town_center/Towncenter_aoe2DE.png@."
            ]
        },
        {
            "villager_count": 21,
            "age": 1,
            "resources": {
                "wood": 5,
                "food": 16,
                "gold": 0,
                "stone": 0
            },
            "notes": [
                "Add 2 @resource/MaleVillDE.jpg@ to @resource/Aoe2de_wood.png@."
            ]
        },
        {
            "villager_count": 21,
            "age": 2,
            "resources": {
                "wood": 10,
                "food": 9,
                "gold": 0,
                "stone": 0
            },
            "notes": [
                "Click up to @age/FeudalAgeIconDE.png@.",
                "Send 5 @resource/MaleVillDE.jpg@ from @town_center/Towncenter_aoe2DE.png@ to build second @lumber_camp/Lumber_camp_aoe2de.png@.",
                "Send 2 @resource/MaleVillDE.jpg@ from @town_center/Towncenter_aoe2DE.png@ to build @other/House_aoe2DE.png@ and @barracks/Barracks_aoe2DE.png@."
            ]
        },
        {
            "villager_count": 30,
            "age": 2,
            "resources": {
                "wood": 10,
                "food": 18,
                "gold": 0,
                "stone": 0
            },
            "notes": [
                "Build a @stable/Stable_aoe2DE.png@ (2 @resource/MaleVillDE.jpg@) and start producing @stable/Scoutcavalry_aoe2DE.png@.",
                "Research @lumber_camp/DoubleBitAxe_aoe2DE.png@ and @mill/HorseCollarDE.png@.",
                "Next @resource/MaleVillDE.jpg@ go to @resource/Aoe2de_wood.png@ (straggler) and then make @mill/FarmDE.png@.",
                "Start the @defensive_structures/Palisade_wall_aoe2de.png@ (also with @other/House_aoe2DE.png@) using 1-3 @resource/MaleVillDE.jpg@."
            ]
        },
        {
            "villager_count": 38,
            "age": 2,
            "resources": {
                "wood": 11,
                "food": 16,
                "gold": 9,
                "stone": 0
            },
            "notes": [
                "Send 8 @resource/MaleVillDE.jpg@ to @resource/Aoe2de_gold.png@ (build @mining_camp/Mining_camp_aoe2de.png@).",
                "Build 2 @archery_range/Archery_range_aoe2DE.png@ and start producing @archery_range/Archer_aoe2DE.png@.",
                "Build a @blacksmith/Blacksmith_aoe2de.png@ and research @blacksmith/FletchingDE.png@ (skip if passive).",
                "After @resource/BerryBushDE.png@, send @resource/MaleVillDE.jpg@ to @resource/Aoe2de_gold.png@ (1), @mill/FarmDE.png@ (2) & @resource/Aoe2de_wood.png@ (1)."
            ]
        },
        {
            "villager_count": -1,
            "age": 3,
            "resources": {
                "wood": -1,
                "food": -1,
                "gold": -1,
                "stone": 0
            },
            "notes": [
                "Click up to @age/CastleAgeIconDE.png@ when you can. Extra @resource/MaleVillDE.jpg@ go to @resource/Aoe2de_wood.png@.",
                "Research @mining_camp/GoldMiningDE.png@, @blacksmith/FletchingDE.png@ (if not done) and @blacksmith/PaddedArcherArmorDE.png@.",
                "Continue massing @archery_range/Archer_aoe2DE.png@."
            ]
        },
        {
            "villager_count": -1,
            "age": 3,
            "resources": {
                "wood": -1,
                "food": -1,
                "gold": -1,
                "stone": 0
            },
            "notes": [
                "Upgrade to @archery_range/ArbalestDE.png@, research @blacksmith/BodkinArrowDE.png@ and @lumber_camp/BowSawDE.png@.",
                "Produce 2-5 @stable/Knight_aoe2DE.png@/@stable/Camelrider_aoe2DE.png@ (to adapt). Research @blacksmith/ScaleBardingArmorDE.png@ (if needed).",
                "Put pressure with @archery_range/Crossbowman_aoe2DE.png@, @stable/Knight_aoe2DE.png@, @stable/Camelrider_aoe2DE.png@. Drop 2 @town_center/Towncenter_aoe2DE.png@ (on @resource/Aoe2de_wood.png@ & @resource/Aoe2de_gold.png@)."
            ]
        }
    ]
}