{
    "name": "cumans double tc kipchaks",
    "civilization": "Cumans",
    "author": "Hera",
    "source": "https://discord.com/invite/RdnZdZRkCq (Hera Discord)",
    "build_order": [{
            "villager_count": 6,
            "age": 1,
            "resources": {
                "wood": 0,
                "food": 6,
                "gold": 0,
                "stone": 0
            },
            "notes": [
                "Build 2 @other/House_aoe2DE.png@.",
                "Send the fitst 6 @resource/MaleVillDE.jpg@ to @animal/Sheep_aoe2DE.png@."
            ]
        },
        {
            "villager_count": 9,
            "age": 1,
            "resources": {
                "wood": 3,
                "food": 6,
                "gold": 0,
                "stone": 0
            },
            "notes": [
                "Build the first @lumber_camp/Lumber_camp_aoe2de.png@.",
                "Send the next 3 @resource/MaleVillDE.jpg@ to @resource/Aoe2de_wood.png@."
            ]
        },
        {
            "villager_count": 10,
            "age": 1,
            "resources": {
                "wood": 3,
                "food": 7,
                "gold": 0,
                "stone": 0
            },
            "notes": [
                "Lure the first @animal/Boar_aoe2DE.png@."
            ]
        },
        {
            "villager_count": 11,
            "age": 1,
            "resources": {
                "wood": 3,
                "food": 8,
                "gold": 0,
                "stone": 0
            },
            "notes": [
                "Build a @other/House_aoe2DE.png@.",
                "Build a @mill/Mill_aoe2de.png@ and gather @resource/BerryBushDE.png@."
            ]
        },
        {
            "villager_count": 12,
            "age": 1,
            "resources": {
                "wood": 3,
                "food": 9,
                "gold": 0,
                "stone": 0
            },
            "notes": [
                "Next @resource/MaleVillDE.jpg@ go to @resource/Aoe2de_food.png@ under @town_center/Towncenter_aoe2DE.png@."
            ]
        },
        {
            "villager_count": 13,
            "age": 1,
            "resources": {
                "wood": 3,
                "food": 10,
                "gold": 0,
                "stone": 0
            },
            "notes": [
                "Lure the second @animal/Boar_aoe2DE.png@."
            ]
        },
        {
            "villager_count": 16,
            "age": 1,
            "resources": {
                "wood": 3,
                "food": 13,
                "gold": 0,
                "stone": 0
            },
            "notes": [
                "Add 3 @resource/MaleVillDE.jpg@ to @resource/Aoe2de_food.png@ under @town_center/Towncenter_aoe2DE.png@ (@animal/Boar_aoe2DE.png@, then @animal/Sheep_aoe2DE.png@)."
            ]
        },
        {
            "villager_count": 19,
            "age": 1,
            "resources": {
                "wood": 3,
                "food": 16,
                "gold": 0,
                "stone": 0
            },
            "notes": [
                "Send 3 @resource/MaleVillDE.jpg@ to @resource/BerryBushDE.png@."
            ]
        },
        {
            "villager_count": 19,
            "age": 2,
            "resources": {
                "wood": 5,
                "food": 14,
                "gold": 0,
                "stone": 0
            },
            "notes": [
                "Research @town_center/LoomDE.png@, then click up to @age/FeudalAgeIconDE.png@.",
                "Send 2 @resource/MaleVillDE.jpg@ from @town_center/Towncenter_aoe2DE.png@ to @lumber_camp/Lumber_camp_aoe2de.png@. Build a @other/House_aoe2DE.png@.",
                "Go to @resource/Aoe2de_wood.png@ (straggler) when running out of @resource/Aoe2de_food.png@ under @town_center/Towncenter_aoe2DE.png@."
            ]
        },
        {
            "villager_count": -1,
            "age": 2,
            "resources": {
                "wood": -1,
                "food": 16,
                "gold": 0,
                "stone": 0
            },
            "notes": [
                "Send 6 @resource/MaleVillDE.jpg@ from @town_center/Towncenter_aoe2DE.png@#1 to build @town_center/Towncenter_aoe2DE.png@#2 (on @resource/Aoe2de_wood.png@, near @resource/Aoe2de_gold.png@/@resource/Aoe2de_stone.png@).",
                "Drop @mill/FarmDE.png@ with @resource/MaleVillDE.jpg@ from @town_center/Towncenter_aoe2DE.png@#1 (when enough @resource/Aoe2de_wood.png@).",
                "Research @lumber_camp/DoubleBitAxe_aoe2DE.png@ and @mill/HorseCollarDE.png@. Send @resource/MaleVillDE.jpg@ from @town_center/Towncenter_aoe2DE.png@#2 to @resource/Aoe2de_wood.png@."
            ]
        },
        {
            "villager_count": -1,
            "age": 3,
            "resources": {
                "wood": -1,
                "food": 16,
                "gold": 8,
                "stone": 6
            },
            "notes": [
                "Around 16 @mill/FarmDE.png@, send next @resource/MaleVillDE.jpg@ to @resource/Aoe2de_gold.png@ (8) and @resource/Aoe2de_stone.png@ (4).",
                "Build @barracks/Barracks_aoe2DE.png@, @stable/Stable_aoe2DE.png@ (or @market/Market_aoe2DE.png@) and @blacksmith/Blacksmith_aoe2de.png@.",
                "Research @town_center/WheelbarrowDE.png@ and click up to @age/CastleAgeIconDE.png@.",
                "Research @blacksmith/FletchingDE.png@ and @stable/BloodlinesDE.png@. Send 2 @resource/MaleVillDE.jpg@ to @resource/Aoe2de_stone.png@."
            ]
        },
        {
            "villager_count": -1,
            "age": -1,
            "resources": {
                "wood": -1,
                "food": -1,
                "gold": -1,
                "stone": -1
            },
            "notes": [
                "Drop a defensive @castle/Castle_aoe2DE.png@, start making @unique_unit/Kipchakicon.png@.",
                "Get upgrades for @unique_unit/Kipchakicon.png@ (@blacksmith/BodkinArrowDE.png@, @blacksmith/PaddedArcherArmorDE.png@...).",
                "Research @lumber_camp/BowSawDE.png@."
            ]
        }
    ]
}