{
    "name": "dravidians drush fc archers",
    "civilization": "Dravidians",
    "author": "Hera",
    "source": "https://www.youtube.com/watch?v=CeIGIkLRcEs",
    "build_order": [{
            "villager_count": 6,
            "age": 1,
            "resources": {
                "wood": 0,
                "food": 6,
                "gold": 0,
                "stone": 0
            },
            "notes": [
                "Build 2 @other/House_aoe2DE.png@.",
                "Send the first 6 @resource/MaleVillDE.jpg@ to @animal/Sheep_aoe2DE.png@."
            ]
        },
        {
            "villager_count": 10,
            "age": 1,
            "resources": {
                "wood": 4,
                "food": 6,
                "gold": 0,
                "stone": 0
            },
            "notes": [
                "Build the first @lumber_camp/Lumber_camp_aoe2de.png@.",
                "Send the next 4 @resource/MaleVillDE.jpg@ to @resource/Aoe2de_wood.png@."
            ]
        },
        {
            "villager_count": 11,
            "age": 1,
            "resources": {
                "wood": 4,
                "food": 7,
                "gold": 0,
                "stone": 0
            },
            "notes": [
                "Lure the first @animal/Boar_aoe2DE.png@."
            ]
        },
        {
            "villager_count": 12,
            "age": 1,
            "resources": {
                "wood": 4,
                "food": 7,
                "gold": 0,
                "stone": 0
            },
            "notes": [
                "Build 2 @other/House_aoe2DE.png@, then a @barracks/Barracks_aoe2DE.png@."
            ]
        },
        {
            "villager_count": 14,
            "age": 1,
            "resources": {
                "wood": 4,
                "food": 9,
                "gold": 0,
                "stone": 0
            },
            "notes": [
                "Add 2 @resource/MaleVillDE.jpg@ to @resource/Aoe2de_food.png@ under @town_center/Towncenter_aoe2DE.png@."
            ]
        },
        {
            "villager_count": 15,
            "age": 1,
            "resources": {
                "wood": 4,
                "food": 10,
                "gold": 0,
                "stone": 0
            },
            "notes": [
                "Lure the second @animal/Boar_aoe2DE.png@."
            ]
        },
        {
            "villager_count": 16,
            "age": 1,
            "resources": {
                "wood": 4,
                "food": 11,
                "gold": 0,
                "stone": 0
            },
            "notes": [
                "Add 1 @resource/MaleVillDE.jpg@ to @resource/Aoe2de_food.png@ under @town_center/Towncenter_aoe2DE.png@. Make 3 @barracks/MilitiaDE.png@.",
                "Build a @mill/Mill_aoe2de.png@ and gather @resource/BerryBushDE.png@ with the @resource/MaleVillDE.jpg@ from @barracks/Barracks_aoe2DE.png@."
            ]
        },
        {
            "villager_count": 20,
            "age": 1,
            "resources": {
                "wood": 4,
                "food": 16,
                "gold": 0,
                "stone": 0
            },
            "notes": [
                "Next @resource/MaleVillDE.jpg@ mines 10 @resource/Aoe2de_gold.png@ without building @mining_camp/Mining_camp_aoe2de.png@.",
                "Once done, send this @resource/MaleVillDE.jpg@ to @resource/Aoe2de_food.png@.",
                "Next @resource/MaleVillDE.jpg@ go to @resource/Aoe2de_food.png@ (@town_center/Towncenter_aoe2DE.png@ or up to 4 @resource/BerryBushDE.png@).",
                "Build a @other/House_aoe2DE.png@. Send the 3 @barracks/MilitiaDE.png@ together."
            ]
        },
        {
            "villager_count": 22,
            "age": 1,
            "resources": {
                "wood": 4,
                "food": 16,
                "gold": 0,
                "stone": 0
            },
            "notes": [
                "Start the @defensive_structures/Palisade_wall_aoe2de.png@ (including @other/House_aoe2DE.png@) with the next 2 @resource/MaleVillDE.jpg@.",
                "Harass with the @barracks/MilitiaDE.png@ and @stable/Scoutcavalry_aoe2DE.png@."
            ]
        },
        {
            "villager_count": 25,
            "age": 1,
            "resources": {
                "wood": 7,
                "food": 16,
                "gold": 0,
                "stone": 0
            },
            "notes": [
                "Send next 2 @resource/MaleVillDE.jpg@ and 1 from @town_center/Towncenter_aoe2DE.png@ to @resource/Aoe2de_wood.png@ (only 1 @lumber_camp/Lumber_camp_aoe2de.png@).",
                "Seed @mill/FarmDE.png@ when @animal/Sheep_aoe2DE.png@ run out, go to @resource/Aoe2de_wood.png@ (straggler) while waiting."
            ]
        },
        {
            "villager_count": 27,
            "age": 1,
            "resources": {
                "wood": 7,
                "food": 14,
                "gold": 4,
                "stone": 0
            },
            "notes": [
                "Send next 2 @resource/MaleVillDE.jpg@ and 2 from @town_center/Towncenter_aoe2DE.png@ to @resource/Aoe2de_gold.png@ (build @mining_camp/Mining_camp_aoe2de.png@)."
            ]
        },
        {
            "villager_count": 27,
            "age": 1,
            "resources": {
                "wood": 7,
                "food": 14,
                "gold": 4,
                "stone": 0
            },
            "notes": [
                "Research @town_center/LoomDE.png@, then click up to @age/FeudalAgeIconDE.png@.",
                "Continue seeding @mill/FarmDE.png@ (up to 14), you get 200 @resource/Aoe2de_wood.png@ in @age/FeudalAgeIconDE.png@.",
                "The @resource/MaleVillDE.jpg@ from @defensive_structures/Palisade_wall_aoe2de.png@ go to @resource/Aoe2de_wood.png@ (straggler).",
                "Continue harassing with @barracks/MilitiaDE.png@ and @stable/Scoutcavalry_aoe2DE.png@."
            ]
        },
        {
            "villager_count": 31,
            "age": 2,
            "resources": {
                "wood": 9,
                "food": 14,
                "gold": 8,
                "stone": 0
            },
            "notes": [
                "Build 2 @archery_range/Archery_range_aoe2DE.png@ with the 2 @resource/MaleVillDE.jpg@ from @defensive_structures/Palisade_wall_aoe2de.png@. Make @archery_range/Archer_aoe2DE.png@.",
                "Build @blacksmith/Blacksmith_aoe2de.png@ with 1 @resource/MaleVillDE.jpg@ from @resource/Aoe2de_gold.png@.",
                "Send next @resource/MaleVillDE.jpg@ to @resource/Aoe2de_gold.png@ (up to 8), next to @resource/Aoe2de_wood.png@."
            ]
        },
        {
            "villager_count": -1,
            "age": 3,
            "resources": {
                "wood": -1,
                "food": -1,
                "gold": -1,
                "stone": -1
            },
            "notes": [
                "Click up to @age/CastleAgeIconDE.png@. Continue massing @archery_range/Archer_aoe2DE.png@.",
                "Research @lumber_camp/DoubleBitAxe_aoe2DE.png@ and @blacksmith/FletchingDE.png@ (skip @mill/HorseCollarDE.png@)."
            ]
        },
        {
            "villager_count": -1,
            "age": -1,
            "resources": {
                "wood": -1,
                "food": -1,
                "gold": -1,
                "stone": -1
            },
            "notes": [
                "Research @archery_range/ArbalestDE.png@, @blacksmith/BodkinArrowDE.png@, @lumber_camp/BowSawDE.png@, then @mill/HorseCollarDE.png@.",
                "Drop @town_center/Towncenter_aoe2DE.png@ when possible, at least 12 @resource/MaleVillDE.jpg@ on @mill/FarmDE.png@.",
                "Continue massing @archery_range/Crossbowman_aoe2DE.png@."
            ]
        }
    ]
}