{
    "name": "drush fc into crossbows",
    "civilization": "Any",
    "author": "Hera",
    "source": "https://discord.com/invite/RdnZdZRkCq (Hera Discord)",
    "build_order": [{
            "villager_count": 6,
            "age": 1,
            "resources": {
                "wood": 0,
                "food": 6,
                "gold": 0,
                "stone": 0
            },
            "notes": [
                "Build 2 @other/House_aoe2DE.png@.",
                "Send the first 6 @resource/MaleVillDE.jpg@ to @animal/Sheep_aoe2DE.png@."
            ]
        },
        {
            "villager_count": 10,
            "age": 1,
            "resources": {
                "wood": 4,
                "food": 6,
                "gold": 0,
                "stone": 0
            },
            "notes": [
                "Build the first @lumber_camp/Lumber_camp_aoe2de.png@.",
                "Send the next 4 @resource/MaleVillDE.jpg@ to @resource/Aoe2de_wood.png@."
            ]
        },
        {
            "villager_count": 11,
            "age": 1,
            "resources": {
                "wood": 4,
                "food": 7,
                "gold": 0,
                "stone": 0
            },
            "notes": [
                "Lure the first @animal/Boar_aoe2DE.png@."
            ]
        },
        {
            "villager_count": 12,
            "age": 1,
            "resources": {
                "wood": 4,
                "food": 8,
                "gold": 0,
                "stone": 0
            },
            "notes": [
                "Build a @other/House_aoe2DE.png@.",
                "Build a @mill/Mill_aoe2de.png@ and gather @resource/BerryBushDE.png@."
            ]
        },
        {
            "villager_count": 14,
            "age": 1,
            "resources": {
                "wood": 4,
                "food": 10,
                "gold": 0,
                "stone": 0
            },
            "notes": [
                "Send 2 @resource/MaleVillDE.jpg@ to @resource/BerryBushDE.png@."
            ]
        },
        {
            "villager_count": 15,
            "age": 1,
            "resources": {
                "wood": 4,
                "food": 11,
                "gold": 0,
                "stone": 0
            },
            "notes": [
                "Lure the second @animal/Boar_aoe2DE.png@."
            ]
        },
        {
            "villager_count": 16,
            "age": 1,
            "resources": {
                "wood": 4,
                "food": 12,
                "gold": 0,
                "stone": 0
            },
            "notes": [
                "Add 1 @resource/MaleVillDE.jpg@ to @resource/BerryBushDE.png@."
            ]
        },
        {
            "villager_count": 17,
            "age": 1,
            "resources": {
                "wood": 4,
                "food": 13,
                "gold": 0,
                "stone": 0
            },
            "notes": [
                "Next @resource/MaleVillDE.jpg@ builds a @other/House_aoe2DE.png@, then a @barracks/Barracks_aoe2DE.png@, then another @other/House_aoe2DE.png@.",
                "Once done, this @resource/MaleVillDE.jpg@ goes to @resource/BerryBushDE.png@."
            ]
        },
        {
            "villager_count": 18,
            "age": 1,
            "resources": {
                "wood": 4,
                "food": 13,
                "gold": 1,
                "stone": 0
            },
            "notes": [
                "Next @resource/MaleVillDE.jpg@ mines 10 @resource/Aoe2de_gold.png@ without building @mining_camp/Mining_camp_aoe2de.png@.",
                "Once done, send this @resource/MaleVillDE.jpg@ to the first @lumber_camp/Lumber_camp_aoe2de.png@."
            ]
        },
        {
            "villager_count": 21,
            "age": 1,
            "resources": {
                "wood": 8,
                "food": 13,
                "gold": 0,
                "stone": 0
            },
            "notes": [
                "Make 3 @barracks/MilitiaDE.png@ and send them forward with the @stable/Scoutcavalry_aoe2DE.png@.",
                "Add 3 @resource/MaleVillDE.jpg@ (+1 from @resource/Aoe2de_gold.png@) to @resource/Aoe2de_wood.png@ (build second @lumber_camp/Lumber_camp_aoe2de.png@ with new @resource/MaleVillDE.jpg@)."
            ]
        },
        {
            "villager_count": 23,
            "age": 1,
            "resources": {
                "wood": 8,
                "food": 15,
                "gold": 0,
                "stone": 0
            },
            "notes": [
                "Next 2 @resource/MaleVillDE.jpg@ go to @resource/Aoe2de_food.png@ under @town_center/Towncenter_aoe2DE.png@ (6 @resource/MaleVillDE.jpg@ on @animal/Sheep_aoe2DE.png@)."
            ]
        },
        {
            "villager_count": 27,
            "age": 1,
            "resources": {
                "wood": 8,
                "food": 15,
                "gold": 4,
                "stone": 0
            },
            "notes": [
                "Build a @mining_camp/Mining_camp_aoe2de.png@. Add 4 @resource/MaleVillDE.jpg@ to @resource/Aoe2de_gold.png@."
            ]
        },
        {
            "villager_count": 27,
            "age": 2,
            "resources": {
                "wood": 8,
                "food": 15,
                "gold": 4,
                "stone": 0
            },
            "notes": [
                "Research @town_center/LoomDE.png@, then click up to @age/FeudalAgeIconDE.png@."
            ]
        },
        {
            "villager_count": 29,
            "age": 2,
            "resources": {
                "wood": 10,
                "food": 15,
                "gold": 4,
                "stone": 0
            },
            "notes": [
                "Build 1 @archery_range/Archery_range_aoe2DE.png@ with 2 @resource/MaleVillDE.jpg@, make @archery_range/Archer_aoe2DE.png@.",
                "Build @blacksmith/Blacksmith_aoe2de.png@ with 1 @resource/MaleVillDE.jpg@.",
                "Send 2 @resource/MaleVillDE.jpg@ to the second @lumber_camp/Lumber_camp_aoe2de.png@."
            ]
        },
        {
            "villager_count": -1,
            "age": 3,
            "resources": {
                "wood": -1,
                "food": -1,
                "gold": -1,
                "stone": -1
            },
            "notes": [
                "Click up to @age/CastleAgeIconDE.png@ (max 20 sec of idle @town_center/Towncenter_aoe2DE.png@).",
                "Research @lumber_camp/DoubleBitAxe_aoe2DE.png@ and @mill/HorseCollarDE.png@."
            ]
        },
        {
            "villager_count": -1,
            "age": -1,
            "resources": {
                "wood": -1,
                "food": -1,
                "gold": -1,
                "stone": -1
            },
            "notes": [
                "Research @archery_range/ArbalestDE.png@, @blacksmith/BodkinArrowDE.png@ and @lumber_camp/BowSawDE.png@.",
                "Drop 2 @town_center/Towncenter_aoe2DE.png@ (extra @resource/Aoe2de_wood.png@ and secondary @resource/Aoe2de_gold.png@).",
                "Research @town_center/WheelbarrowDE.png@ (around min 21)."
            ]
        }
    ]
}