{
    "name": "drush into archers",
    "civilization": "Any",
    "author": "Hera",
    "source": "https://discord.com/invite/RdnZdZRkCq (Hera Discord)",
    "build_order": [{
            "villager_count": 6,
            "age": 1,
            "resources": {
                "wood": 0,
                "food": 6,
                "gold": 0,
                "stone": 0
            },
            "notes": [
                "Build 2 @other/House_aoe2DE.png@.",
                "Send the first 6 @resource/MaleVillDE.jpg@ to @animal/Sheep_aoe2DE.png@."
            ]
        },
        {
            "villager_count": 10,
            "age": 1,
            "resources": {
                "wood": 4,
                "food": 6,
                "gold": 0,
                "stone": 0
            },
            "notes": [
                "Build the first @lumber_camp/Lumber_camp_aoe2de.png@.",
                "Send the next 4 @resource/MaleVillDE.jpg@ to @resource/Aoe2de_wood.png@."
            ]
        },
        {
            "villager_count": 11,
            "age": 1,
            "resources": {
                "wood": 4,
                "food": 7,
                "gold": 0,
                "stone": 0
            },
            "notes": [
                "Lure the first @animal/Boar_aoe2DE.png@."
            ]
        },
        {
            "villager_count": 12,
            "age": 1,
            "resources": {
                "wood": 4,
                "food": 8,
                "gold": 0,
                "stone": 0
            },
            "notes": [
                "Build a @other/House_aoe2DE.png@.",
                "Build a @mill/Mill_aoe2de.png@ and gather @resource/BerryBushDE.png@."
            ]
        },
        {
            "villager_count": 14,
            "age": 1,
            "resources": {
                "wood": 4,
                "food": 10,
                "gold": 0,
                "stone": 0
            },
            "notes": [
                "Send 2 @resource/MaleVillDE.jpg@ to @resource/BerryBushDE.png@."
            ]
        },
        {
            "villager_count": 15,
            "age": 1,
            "resources": {
                "wood": 4,
                "food": 11,
                "gold": 0,
                "stone": 0
            },
            "notes": [
                "Lure the second @animal/Boar_aoe2DE.png@."
            ]
        },
        {
            "villager_count": 16,
            "age": 1,
            "resources": {
                "wood": 4,
                "food": 12,
                "gold": 0,
                "stone": 0
            },
            "notes": [
                "Add 1 @resource/MaleVillDE.jpg@ to @resource/BerryBushDE.png@."
            ]
        },
        {
            "villager_count": 17,
            "age": 1,
            "resources": {
                "wood": 4,
                "food": 12,
                "gold": 0,
                "stone": 0
            },
            "notes": [
                "Next @resource/MaleVillDE.jpg@ builds a @other/House_aoe2DE.png@, then a @barracks/Barracks_aoe2DE.png@, then another @other/House_aoe2DE.png@.",
                "Once done, start the @defensive_structures/Palisade_wall_aoe2de.png@ with this @resource/MaleVillDE.jpg@."
            ]
        },
        {
            "villager_count": 18,
            "age": 1,
            "resources": {
                "wood": 4,
                "food": 12,
                "gold": 1,
                "stone": 0
            },
            "notes": [
                "Next @resource/MaleVillDE.jpg@ mines 10 @resource/Aoe2de_gold.png@ without building @mining_camp/Mining_camp_aoe2de.png@.",
                "Once done, send this @resource/MaleVillDE.jpg@ to @resource/Aoe2de_food.png@ under @town_center/Towncenter_aoe2DE.png@."
            ]
        },
        {
            "villager_count": 19,
            "age": 1,
            "resources": {
                "wood": 5,
                "food": 12,
                "gold": 1,
                "stone": 0
            },
            "notes": [
                "Make 3 @barracks/MilitiaDE.png@ and send them forward with the @stable/Scoutcavalry_aoe2DE.png@.",
                "Add 1 @resource/MaleVillDE.jpg@ to @resource/Aoe2de_wood.png@ (first @lumber_camp/Lumber_camp_aoe2de.png@)."
            ]
        },
        {
            "villager_count": 24,
            "age": 1,
            "resources": {
                "wood": 5,
                "food": 18,
                "gold": 0,
                "stone": 0
            },
            "notes": [
                "Next 5 @resource/MaleVillDE.jpg@ (+ @resource/Aoe2de_gold.png@ one) go to @resource/Aoe2de_food.png@ under @town_center/Towncenter_aoe2DE.png@.",
                "Make 4 @mill/FarmDE.png@ before @animal/Sheep_aoe2DE.png@ run out."
            ]
        },
        {
            "villager_count": 24,
            "age": 2,
            "resources": {
                "wood": 10,
                "food": 10,
                "gold": 3,
                "stone": 0
            },
            "notes": [
                "Research @town_center/LoomDE.png@, then click up to @age/FeudalAgeIconDE.png@.",
                "Send 8 @resource/MaleVillDE.jpg@ from @town_center/Towncenter_aoe2DE.png@ to @resource/Aoe2de_wood.png@ (5) and to @resource/Aoe2de_gold.png@ (3).",
                "Build second @lumber_camp/Lumber_camp_aoe2de.png@ and first @mining_camp/Mining_camp_aoe2de.png@ with these @resource/MaleVillDE.jpg@.",
                "As @resource/Aoe2de_food.png@ from @town_center/Towncenter_aoe2DE.png@ runs out, send @resource/MaleVillDE.jpg@ to @resource/Aoe2de_wood.png@ (straggler)."
            ]
        },
        {
            "villager_count": 28,
            "age": 2,
            "resources": {
                "wood": 10,
                "food": 10,
                "gold": 7,
                "stone": 0
            },
            "notes": [
                "Research @lumber_camp/DoubleBitAxe_aoe2DE.png@ and build 2 @archery_range/Archery_range_aoe2DE.png@ at front.",
                "Make @archery_range/Archer_aoe2DE.png@ and a few @barracks/Spearman_aoe2DE.png@ if needed.",
                "Build @other/House_aoe2DE.png@ and continue @defensive_structures/Palisade_wall_aoe2de.png@.",
                "Build @blacksmith/Blacksmith_aoe2de.png@, research @blacksmith/FletchingDE.png@. Then, send out @archery_range/Archer_aoe2DE.png@.",
                "Send the next 4 @resource/MaleVillDE.jpg@ to @resource/Aoe2de_gold.png@."
            ]
        },
        {
            "villager_count": -1,
            "age": 3,
            "resources": {
                "wood": -1,
                "food": -1,
                "gold": -1,
                "stone": -1
            },
            "notes": [
                "Make @mill/FarmDE.png@ with 4-5 new @resource/MaleVillDE.jpg@ until about 13, then get @town_center/WheelbarrowDE.png@.",
                "When @resource/BerryBushDE.png@ run out, 2 @resource/MaleVillDE.jpg@ go to @resource/Aoe2de_gold.png@ and 2 go to @resource/Aoe2de_wood.png@ or @mill/FarmDE.png@.",
                "Click up to @age/CastleAgeIconDE.png@. Keep massing @archery_range/Archer_aoe2DE.png@.",
                "Research @mill/HorseCollarDE.png@, @mining_camp/GoldMiningDE.png@ and @blacksmith/PaddedArcherArmorDE.png@."
            ]
        },
        {
            "villager_count": -1,
            "age": -1,
            "resources": {
                "wood": -1,
                "food": -1,
                "gold": -1,
                "stone": -1
            },
            "notes": [
                "Research @archery_range/ArbalestDE.png@, @blacksmith/BodkinArrowDE.png@ and @lumber_camp/BowSawDE.png@.",
                "Drop 2 @town_center/Towncenter_aoe2DE.png@ (extra @resource/Aoe2de_wood.png@ and secondary @resource/Aoe2de_gold.png@)."
            ]
        }
    ]
}