{
    "name": "empire wars archers crossbow",
    "civilization": "Any",
    "author": "Hera",
    "source": "https://discord.com/invite/RdnZdZRkCq (Hera Discord)",
    "build_order": [{
            "villager_count": 27,
            "age": 2,
            "resources": {
                "wood": 12,
                "food": 11,
                "gold": 4,
                "stone": 0
            },
            "notes": [
                "The @resource/MaleVillDE.jpg@ under @town_center/Towncenter_aoe2DE.png@ go to @animal/Sheep_aoe2DE.png@.",
                "Build 1 @archery_range/Archery_range_aoe2DE.png@ with a @resource/MaleVillDE.jpg@ from @resource/Aoe2de_wood.png@, then 2 @other/House_aoe2DE.png@.",
                "Scout your opponents with @stable/Scoutcavalry_aoe2DE.png@. Research @lumber_camp/DoubleBitAxe_aoe2DE.png@."
            ]
        },
        {
            "villager_count": -1,
            "age": 2,
            "resources": {
                "wood": 12,
                "food": -1,
                "gold": 4,
                "stone": 0
            },
            "notes": [
                "Next @resource/MaleVillDE.jpg@ go to @animal/Sheep_aoe2DE.png@.",
                "Make @archery_range/Archer_aoe2DE.png@ and 2-3 @barracks/Spearman_aoe2DE.png@ (1 if only opponent @archery_range/Archer_aoe2DE.png@).",
                "Start the @defensive_structures/Palisade_wall_aoe2de.png@ (including @other/House_aoe2DE.png@) with 2-3 @resource/MaleVillDE.jpg@. Research @blacksmith/FletchingDE.png@.",
                "Keep 4-5 @resource/MaleVillDE.jpg@ on @animal/Sheep_aoe2DE.png@. The others (under @town_center/Towncenter_aoe2DE.png@) seed @mill/FarmDE.png@.",
                "Move with @archery_range/Archer_aoe2DE.png@ & @barracks/Spearman_aoe2DE.png@ when fully @defensive_structures/Palisade_wall_aoe2de.png@ (sooner ok but risky)."
            ]
        },
        {
            "villager_count": 42,
            "age": 2,
            "resources": {
                "wood": 15,
                "food": 18,
                "gold": 9,
                "stone": 0
            },
            "notes": [
                "When depleted, send 5 @resource/MaleVillDE.jpg@ from @animal/Sheep_aoe2DE.png@ to @resource/Aoe2de_gold.png@.",
                "Next @resource/MaleVillDE.jpg@ go to @mill/FarmDE.png@ (up to 14), then @resource/Aoe2de_wood.png@."
            ]
        },
        {
            "villager_count": 42,
            "age": 3,
            "resources": {
                "wood": -1,
                "food": -1,
                "gold": -1,
                "stone": -1
            },
            "notes": [
                "Click up to @age/CastleAgeIconDE.png@. Build second @archery_range/Archery_range_aoe2DE.png@.",
                "Make @archery_range/Archer_aoe2DE.png@. Research @mill/HorseCollarDE.png@, @mining_camp/GoldMiningDE.png@ and @blacksmith/PaddedArcherArmorDE.png@",
                "Add 1 extra @archery_range/Archery_range_aoe2DE.png@ or @stable/Stable_aoe2DE.png@.",
                "Once in @age/CastleAgeIconDE.png@, research @blacksmith/BodkinArrowDE.png@, @archery_range/ArbalestDE.png@ and @lumber_camp/BowSawDE.png@."
            ]
        }
    ]
}