{
    "name": "franks 19 pop scouts",
    "civilization": "Franks",
    "author": "Hera",
    "source": "https://discord.com/invite/RdnZdZRkCq (Hera Discord)",
    "build_order": [{
            "villager_count": 6,
            "age": 1,
            "resources": {
                "wood": 0,
                "food": 6,
                "gold": 0,
                "stone": 0
            },
            "notes": [
                "Build 2 @other/House_aoe2DE.png@.",
                "Send the first 6 @resource/MaleVillDE.jpg@ to @animal/Sheep_aoe2DE.png@."
            ]
        },
        {
            "villager_count": 8,
            "age": 1,
            "resources": {
                "wood": 2,
                "food": 6,
                "gold": 0,
                "stone": 0
            },
            "notes": [
                "Build the first @lumber_camp/Lumber_camp_aoe2de.png@.",
                "Send the next 2 @resource/MaleVillDE.jpg@ to @resource/Aoe2de_wood.png@."
            ]
        },
        {
            "villager_count": 9,
            "age": 1,
            "resources": {
                "wood": 2,
                "food": 7,
                "gold": 0,
                "stone": 0
            },
            "notes": [
                "Lure the first @animal/Boar_aoe2DE.png@."
            ]
        },
        {
            "villager_count": 10,
            "age": 1,
            "resources": {
                "wood": 2,
                "food": 8,
                "gold": 0,
                "stone": 0
            },
            "notes": [
                "Next @resource/MaleVillDE.jpg@ goes to @resource/Aoe2de_food.png@ under @town_center/Towncenter_aoe2DE.png@."
            ]
        },
        {
            "villager_count": 11,
            "age": 1,
            "resources": {
                "wood": 3,
                "food": 8,
                "gold": 0,
                "stone": 0
            },
            "notes": [
                "Add 1 @resource/MaleVillDE.jpg@ to @resource/Aoe2de_wood.png@."
            ]
        },
        {
            "villager_count": 12,
            "age": 1,
            "resources": {
                "wood": 3,
                "food": 9,
                "gold": 0,
                "stone": 0
            },
            "notes": [
                "Build a @other/House_aoe2DE.png@.",
                "Build a @mill/Mill_aoe2de.png@ and gather @resource/BerryBushDE.png@."
            ]
        },
        {
            "villager_count": 13,
            "age": 1,
            "resources": {
                "wood": 3,
                "food": 10,
                "gold": 0,
                "stone": 0
            },
            "notes": [
                "Lure the second @animal/Boar_aoe2DE.png@."
            ]
        },
        {
            "villager_count": 14,
            "age": 1,
            "resources": {
                "wood": 3,
                "food": 11,
                "gold": 0,
                "stone": 0
            },
            "notes": [
                "Next @resource/MaleVillDE.jpg@ goes to @resource/Aoe2de_food.png@ under @town_center/Towncenter_aoe2DE.png@."
            ]
        },
        {
            "villager_count": 17,
            "age": 1,
            "resources": {
                "wood": 3,
                "food": 14,
                "gold": 0,
                "stone": 0
            },
            "notes": [
                "Send 3 @resource/MaleVillDE.jpg@ to @resource/BerryBushDE.png@."
            ]
        },
        {
            "villager_count": 18,
            "age": 1,
            "resources": {
                "wood": 4,
                "food": 14,
                "gold": 0,
                "stone": 0
            },
            "notes": [
                "Add 1 @resource/MaleVillDE.jpg@ to @resource/Aoe2de_wood.png@."
            ]
        },
        {
            "villager_count": 18,
            "age": 2,
            "resources": {
                "wood": 9,
                "food": 9,
                "gold": 0,
                "stone": 0
            },
            "notes": [
                "Research @town_center/LoomDE.png@, then click up to @age/FeudalAgeIconDE.png@.",
                "Send 5 @resource/MaleVillDE.jpg@ from @town_center/Towncenter_aoe2DE.png@ to build second @lumber_camp/Lumber_camp_aoe2de.png@.",
                "Build a @other/House_aoe2DE.png@ and a @barracks/Barracks_aoe2DE.png@."
            ]
        },
        {
            "villager_count": -1,
            "age": 2,
            "resources": {
                "wood": -1,
                "food": -1,
                "gold": 5,
                "stone": 0
            },
            "notes": [
                "Build a @stable/Stable_aoe2DE.png@ and produce @stable/Scoutcavalry_aoe2DE.png@.",
                "Start the @defensive_structures/Palisade_wall_aoe2de.png@ with @resource/MaleVillDE.jpg@ from @resource/Aoe2de_wood.png@.",
                "Research @lumber_camp/DoubleBitAxe_aoe2DE.png@ (free @mill/HorseCollarDE.png@). Drop @mill/FarmDE.png@ when you can.",
                "Send 5 @resource/MaleVillDE.jpg@ to @resource/Aoe2de_gold.png@ (around min 14)."
            ]
        },
        {
            "villager_count": -1,
            "age": 3,
            "resources": {
                "wood": -1,
                "food": -1,
                "gold": 6,
                "stone": 0
            },
            "notes": [
                "Build a @blacksmith/Blacksmith_aoe2de.png@ and research @town_center/WheelbarrowDE.png@.",
                "Send @resource/MaleVillDE.jpg@ from @resource/BerryBushDE.png@ to @mill/FarmDE.png@ when depleted.",
                "Click up to @age/CastleAgeIconDE.png@. Research @blacksmith/Forging_aoe2de.png@, @blacksmith/ScaleBardingArmorDE.png@ and @mining_camp/GoldMiningDE.png@.",
                "Add 1 @resource/MaleVillDE.jpg@ to @resource/Aoe2de_gold.png@. Build a second @stable/Stable_aoe2DE.png@."
            ]
        },
        {
            "villager_count": -1,
            "age": 3,
            "resources": {
                "wood": -1,
                "food": -1,
                "gold": -1,
                "stone": -1
            },
            "notes": [
                "Produce @stable/Knight_aoe2DE.png@ from 2 @stable/Stable_aoe2DE.png@.",
                "Drop 2 @town_center/Towncenter_aoe2DE.png@ on @resource/Aoe2de_wood.png@ & @resource/Aoe2de_gold.png@. Research @lumber_camp/BowSawDE.png@."
            ]
        }
    ]
}