{
    "name": "huns scouts into archers",
    "civilization": "Huns",
    "author": "Hera",
    "source": "https://discord.com/invite/RdnZdZRkCq (Hera Discord)",
    "build_order": [{
            "villager_count": 6,
            "age": 1,
            "resources": {
                "wood": 0,
                "food": 6,
                "gold": 0,
                "stone": 0
            },
            "notes": [
                "Send the fitst 6 @resource/MaleVillDE.jpg@ to @animal/Sheep_aoe2DE.png@ (no @other/House_aoe2DE.png@ for @civilization/CivIcon-Huns.png@)."
            ]
        },
        {
            "villager_count": 9,
            "age": 1,
            "resources": {
                "wood": 3,
                "food": 6,
                "gold": 0,
                "stone": 0
            },
            "notes": [
                "Build the first @lumber_camp/Lumber_camp_aoe2de.png@.",
                "Send the next 3 @resource/MaleVillDE.jpg@ to @resource/Aoe2de_wood.png@."
            ]
        },
        {
            "villager_count": 10,
            "age": 1,
            "resources": {
                "wood": 3,
                "food": 7,
                "gold": 0,
                "stone": 0
            },
            "notes": [
                "Lure the first @animal/Boar_aoe2DE.png@."
            ]
        },
        {
            "villager_count": 11,
            "age": 1,
            "resources": {
                "wood": 3,
                "food": 8,
                "gold": 0,
                "stone": 0
            },
            "notes": [
                "Next @resource/MaleVillDE.jpg@ goes to @resource/Aoe2de_food.png@ under @town_center/Towncenter_aoe2DE.png@."
            ]
        },
        {
            "villager_count": 14,
            "age": 1,
            "resources": {
                "wood": 3,
                "food": 11,
                "gold": 0,
                "stone": 0
            },
            "notes": [
                "Build a @mill/Mill_aoe2de.png@ and gather @resource/BerryBushDE.png@ with the next 3 @resource/MaleVillDE.jpg@."
            ]
        },
        {
            "villager_count": 15,
            "age": 1,
            "resources": {
                "wood": 3,
                "food": 12,
                "gold": 0,
                "stone": 0
            },
            "notes": [
                "Lure the second @animal/Boar_aoe2DE.png@."
            ]
        },
        {
            "villager_count": 16,
            "age": 1,
            "resources": {
                "wood": 3,
                "food": 13,
                "gold": 0,
                "stone": 0
            },
            "notes": [
                "Add 1 @resource/MaleVillDE.jpg@ to @resource/BerryBushDE.png@."
            ]
        },
        {
            "villager_count": 17,
            "age": 1,
            "resources": {
                "wood": 3,
                "food": 14,
                "gold": 0,
                "stone": 0
            },
            "notes": [
                "Add 1 @resource/MaleVillDE.jpg@ to @resource/Aoe2de_food.png@ under @town_center/Towncenter_aoe2DE.png@."
            ]
        },
        {
            "villager_count": 19,
            "age": 1,
            "resources": {
                "wood": 5,
                "food": 14,
                "gold": 0,
                "stone": 0
            },
            "notes": [
                "Add 2 @resource/MaleVillDE.jpg@ to @resource/Aoe2de_wood.png@."
            ]
        },
        {
            "villager_count": 20,
            "age": 1,
            "resources": {
                "wood": 6,
                "food": 14,
                "gold": 0,
                "stone": 0
            },
            "notes": [
                "Build a second @lumber_camp/Lumber_camp_aoe2de.png@. Add 1 @resource/MaleVillDE.jpg@ to @resource/Aoe2de_wood.png@."
            ]
        },
        {
            "villager_count": 20,
            "age": 2,
            "resources": {
                "wood": 9,
                "food": 11,
                "gold": 0,
                "stone": 0
            },
            "notes": [
                "Research @town_center/LoomDE.png@, then click up to @age/FeudalAgeIconDE.png@.",
                "Send 3 @resource/MaleVillDE.jpg@ from @town_center/Towncenter_aoe2DE.png@ to second @lumber_camp/Lumber_camp_aoe2de.png@.",
                "Build @barracks/Barracks_aoe2DE.png@ at 60% up."
            ]
        },
        {
            "villager_count": 21,
            "age": 2,
            "resources": {
                "wood": 10,
                "food": 11,
                "gold": 0,
                "stone": 0
            },
            "notes": [
                "Build a @stable/Stable_aoe2DE.png@ with 2 @resource/MaleVillDE.jpg@ and start making @stable/Scoutcavalry_aoe2DE.png@.",
                "Research @lumber_camp/DoubleBitAxe_aoe2DE.png@ and @mill/HorseCollarDE.png@.",
                "Next @resource/MaleVillDE.jpg@ goes to @resource/Aoe2de_wood.png@ (5 on each @lumber_camp/Lumber_camp_aoe2de.png@)."
            ]
        },
        {
            "villager_count": 29,
            "age": 2,
            "resources": {
                "wood": 10,
                "food": 19,
                "gold": 0,
                "stone": 0
            },
            "notes": [
                "Drop @mill/FarmDE.png@ when you have enough @resource/Aoe2de_wood.png@."
            ]
        },
        {
            "villager_count": 36,
            "age": 2,
            "resources": {
                "wood": 10,
                "food": 19,
                "gold": 7,
                "stone": 0
            },
            "notes": [
                "Start taking @resource/Aoe2de_gold.png@. Build 2 @archery_range/Archery_range_aoe2DE.png@. Produce @archery_range/Archer_aoe2DE.png@."
            ]
        },
        {
            "villager_count": 39,
            "age": 2,
            "resources": {
                "wood": 10,
                "food": 19,
                "gold": 10,
                "stone": 0
            },
            "notes": [
                "Research @town_center/WheelbarrowDE.png@. Build a @blacksmith/Blacksmith_aoe2de.png@ and research @blacksmith/FletchingDE.png@.",
                "Send 3 extra @resource/MaleVillDE.jpg@ to @resource/Aoe2de_gold.png@."
            ]
        },
        {
            "villager_count": -1,
            "age": 3,
            "resources": {
                "wood": -1,
                "food": -1,
                "gold": -1,
                "stone": -1
            },
            "notes": [
                "Click up to @age/CastleAgeIconDE.png@. Research @blacksmith/PaddedArcherArmorDE.png@ and @mining_camp/GoldMiningDE.png@.",
                "Keep massing @archery_range/Archer_aoe2DE.png@. Build a third @archery_range/Archery_range_aoe2DE.png@."
            ]
        },
        {
            "villager_count": -1,
            "age": -1,
            "resources": {
                "wood": -1,
                "food": -1,
                "gold": -1,
                "stone": -1
            },
            "notes": [
                "Upgrade to @archery_range/Crossbowman_aoe2DE.png@. Research @blacksmith/BodkinArrowDE.png@ and @lumber_camp/BowSawDE.png@.",
                "Build a @university/University_AoE2_DE.png@ and research @university/BallisticsDE.png@ (stop training army).",
                "Once @university/BallisticsDE.png@ is done, produce @archery_range/Crossbowman_aoe2DE.png@ and @archery_range/Cavalryarcher_aoe2DE.png@."
            ]
        }
    ]
}