{
    "name": "japanese 20 pop man-at-arms",
    "civilization": "Japanese",
    "author": "Hera",
    "source": "https://discord.com/invite/RdnZdZRkCq (Hera Discord)",
    "build_order": [{
            "villager_count": 6,
            "age": 1,
            "resources": {
                "wood": 0,
                "food": 6,
                "gold": 0,
                "stone": 0
            },
            "notes": [
                "Build 2 @other/House_aoe2DE.png@.",
                "Send the first 6 @resource/MaleVillDE.jpg@ to @animal/Sheep_aoe2DE.png@."
            ]
        },
        {
            "villager_count": 9,
            "age": 1,
            "resources": {
                "wood": 3,
                "food": 6,
                "gold": 0,
                "stone": 0
            },
            "notes": [
                "Build the first @lumber_camp/Lumber_camp_aoe2de.png@.",
                "Send the next 3 @resource/MaleVillDE.jpg@ to @resource/Aoe2de_wood.png@."
            ]
        },
        {
            "villager_count": 10,
            "age": 1,
            "resources": {
                "wood": 3,
                "food": 7,
                "gold": 0,
                "stone": 0
            },
            "notes": [
                "Lure the first @animal/Boar_aoe2DE.png@."
            ]
        },
        {
            "villager_count": 11,
            "age": 1,
            "resources": {
                "wood": 3,
                "food": 8,
                "gold": 0,
                "stone": 0
            },
            "notes": [
                "Build a @other/House_aoe2DE.png@.",
                "Build a @mill/Mill_aoe2de.png@ and gather @resource/BerryBushDE.png@."
            ]
        },
        {
            "villager_count": 13,
            "age": 1,
            "resources": {
                "wood": 3,
                "food": 10,
                "gold": 0,
                "stone": 0
            },
            "notes": [
                "Send 2 @resource/MaleVillDE.jpg@ to @resource/BerryBushDE.png@.",
                "Push 1 @animal/Deer_aoe2DE.png@ with @stable/Scoutcavalry_aoe2DE.png@ (optional)."
            ]
        },
        {
            "villager_count": 14,
            "age": 1,
            "resources": {
                "wood": 3,
                "food": 11,
                "gold": 0,
                "stone": 0
            },
            "notes": [
                "Lure the second @animal/Boar_aoe2DE.png@."
            ]
        },
        {
            "villager_count": 15,
            "age": 1,
            "resources": {
                "wood": 3,
                "food": 12,
                "gold": 0,
                "stone": 0
            },
            "notes": [
                "Add 1 @resource/MaleVillDE.jpg@ to @resource/BerryBushDE.png@."
            ]
        },
        {
            "villager_count": 16,
            "age": 1,
            "resources": {
                "wood": 3,
                "food": 13,
                "gold": 0,
                "stone": 0
            },
            "notes": [
                "Add 1 @resource/MaleVillDE.jpg@ to @resource/Aoe2de_food.png@ under @town_center/Towncenter_aoe2DE.png@."
            ]
        },
        {
            "villager_count": 17,
            "age": 1,
            "resources": {
                "wood": 3,
                "food": 13,
                "gold": 0,
                "stone": 0
            },
            "notes": [
                "Send next @resource/MaleVillDE.jpg@ to build a @other/House_aoe2DE.png@, then a @barracks/Barracks_aoe2DE.png@.",
                "After that, build @other/House_aoe2DE.png@ & @defensive_structures/Palisade_wall_aoe2de.png@ with this @resource/MaleVillDE.jpg@."
            ]
        },
        {
            "villager_count": 19,
            "age": 1,
            "resources": {
                "wood": 3,
                "food": 13,
                "gold": 2,
                "stone": 0
            },
            "notes": [
                "Build a @mining_camp/Mining_camp_aoe2de.png@. Send the next 2 @resource/MaleVillDE.jpg@ to @resource/Aoe2de_gold.png@."
            ]
        },
        {
            "villager_count": 19,
            "age": 2,
            "resources": {
                "wood": 9,
                "food": 7,
                "gold": 2,
                "stone": 0
            },
            "notes": [
                "Research @town_center/LoomDE.png@, then click up to @age/FeudalAgeIconDE.png@.",
                "Send 6 @resource/MaleVillDE.jpg@ from @town_center/Towncenter_aoe2DE.png@ to @resource/Aoe2de_wood.png@ (4 on second @lumber_camp/Lumber_camp_aoe2de.png@).",
                "Make 3 @barracks/MilitiaDE.png@ and send them forward."
            ]
        },
        {
            "villager_count": 22,
            "age": 2,
            "resources": {
                "wood": 9,
                "food": 7,
                "gold": 5,
                "stone": 0
            },
            "notes": [
                "Research @barracks/ManAtArmsUpgDE.png@, then @lumber_camp/DoubleBitAxe_aoe2DE.png@.",
                "Seed @mill/FarmDE.png@ with @resource/MaleVillDE.jpg@ from @town_center/Towncenter_aoe2DE.png@.",
                "Build the first @archery_range/Archery_range_aoe2DE.png@ and @other/House_aoe2DE.png@ with the building @resource/MaleVillDE.jpg@.",
                "Send the next 3 @resource/MaleVillDE.jpg@ to @resource/Aoe2de_gold.png@."
            ]
        },
        {
            "villager_count": 37,
            "age": 2,
            "resources": {
                "wood": 9,
                "food": 18,
                "gold": 9,
                "stone": 0
            },
            "notes": [
                "Produce @archery_range/Archer_aoe2DE.png@ from 1 @archery_range/Archery_range_aoe2DE.png@ (move after @blacksmith/FletchingDE.png@ and full @defensive_structures/Palisade_wall_aoe2de.png@).",
                "After 6 @mill/FarmDE.png@, build a @blacksmith/Blacksmith_aoe2de.png@, and research @blacksmith/FletchingDE.png@.",
                "After 14 @mill/FarmDE.png@, send 4 @resource/MaleVillDE.jpg@ to @resource/Aoe2de_gold.png@."
            ]
        },
        {
            "villager_count": 37,
            "age": 2,
            "resources": {
                "wood": 11,
                "food": 16,
                "gold": 9,
                "stone": 0
            },
            "notes": [
                "After @resource/BerryBushDE.png@, send 2 @resource/MaleVillDE.jpg@ to @mill/FarmDE.png@ and 2 to @resource/Aoe2de_wood.png@.",
                "Build a second @archery_range/Archery_range_aoe2DE.png@ and mass more @archery_range/Archer_aoe2DE.png@.",
                "Click up to @age/CastleAgeIconDE.png@. Research @mill/HorseCollarDE.png@, @mining_camp/GoldMiningDE.png@ and @blacksmith/PaddedArcherArmorDE.png@."
            ]
        },
        {
            "villager_count": -1,
            "age": 3,
            "resources": {
                "wood": -1,
                "food": -1,
                "gold": -1,
                "stone": -1
            },
            "notes": [
                "Research @lumber_camp/BowSawDE.png@, @archery_range/ArbalestDE.png@ and @blacksmith/BodkinArrowDE.png@.",
                "Attack (or defend) with @archery_range/Crossbowman_aoe2DE.png@ after upgrades.",
                "Drop 2 @town_center/Towncenter_aoe2DE.png@ when you can (@resource/Aoe2de_wood.png@, then @resource/Aoe2de_gold.png@)."
            ]
        }
    ]
}