{
    "name": "magyars scouts cav archers",
    "civilization": "Magyars",
    "author": "Hera",
    "source": "https://discord.com/invite/RdnZdZRkCq (Hera Discord)",
    "build_order": [{
            "villager_count": 6,
            "age": 1,
            "resources": {
                "wood": 0,
                "food": 6,
                "gold": 0,
                "stone": 0
            },
            "notes": [
                "Build 2 @other/House_aoe2DE.png@.",
                "Send the fitst 6 @resource/MaleVillDE.jpg@ to @animal/Sheep_aoe2DE.png@."
            ]
        },
        {
            "villager_count": 9,
            "age": 1,
            "resources": {
                "wood": 3,
                "food": 6,
                "gold": 0,
                "stone": 0
            },
            "notes": [
                "Build the first @lumber_camp/Lumber_camp_aoe2de.png@.",
                "Send the next 3 @resource/MaleVillDE.jpg@ to @resource/Aoe2de_wood.png@."
            ]
        },
        {
            "villager_count": 10,
            "age": 1,
            "resources": {
                "wood": 3,
                "food": 7,
                "gold": 0,
                "stone": 0
            },
            "notes": [
                "Lure the first @animal/Boar_aoe2DE.png@."
            ]
        },
        {
            "villager_count": 11,
            "age": 1,
            "resources": {
                "wood": 3,
                "food": 8,
                "gold": 0,
                "stone": 0
            },
            "notes": [
                "Build a @other/House_aoe2DE.png@.",
                "Build a @mill/Mill_aoe2de.png@ and gather @resource/BerryBushDE.png@."
            ]
        },
        {
            "villager_count": 13,
            "age": 1,
            "resources": {
                "wood": 3,
                "food": 10,
                "gold": 0,
                "stone": 0
            },
            "notes": [
                "Send 2 @resource/MaleVillDE.jpg@ to @resource/BerryBushDE.png@."
            ]
        },
        {
            "villager_count": 14,
            "age": 1,
            "resources": {
                "wood": 3,
                "food": 11,
                "gold": 0,
                "stone": 0
            },
            "notes": [
                "Lure the second @animal/Boar_aoe2DE.png@."
            ]
        },
        {
            "villager_count": 15,
            "age": 1,
            "resources": {
                "wood": 3,
                "food": 12,
                "gold": 0,
                "stone": 0
            },
            "notes": [
                "Add 1 @resource/MaleVillDE.jpg@ to @resource/BerryBushDE.png@."
            ]
        },
        {
            "villager_count": 18,
            "age": 1,
            "resources": {
                "wood": 3,
                "food": 15,
                "gold": 0,
                "stone": 0
            },
            "notes": [
                "Next 3 @resource/MaleVillDE.jpg@ go to @resource/Aoe2de_food.png@ under @town_center/Towncenter_aoe2DE.png@."
            ]
        },
        {
            "villager_count": 19,
            "age": 1,
            "resources": {
                "wood": 4,
                "food": 15,
                "gold": 0,
                "stone": 0
            },
            "notes": [
                "Add 1 @resource/MaleVillDE.jpg@ to @resource/Aoe2de_wood.png@."
            ]
        },
        {
            "villager_count": 19,
            "age": 2,
            "resources": {
                "wood": 9,
                "food": 10,
                "gold": 0,
                "stone": 0
            },
            "notes": [
                "Research @town_center/LoomDE.png@, then click up to @age/FeudalAgeIconDE.png@.",
                "Send 5 @resource/MaleVillDE.jpg@ from @town_center/Towncenter_aoe2DE.png@ to @resource/Aoe2de_wood.png@, 4 of them on new @lumber_camp/Lumber_camp_aoe2de.png@.",
                "Build a @other/House_aoe2DE.png@ and a @barracks/Barracks_aoe2DE.png@ with 2 @resource/MaleVillDE.jpg@ from @town_center/Towncenter_aoe2DE.png@."
            ]
        },
        {
            "villager_count": 28,
            "age": 2,
            "resources": {
                "wood": 10,
                "food": 18,
                "gold": 0,
                "stone": 0
            },
            "notes": [
                "Build a @stable/Stable_aoe2DE.png@ with 2 @resource/MaleVillDE.jpg@. Research @lumber_camp/DoubleBitAxe_aoe2DE.png@ and @mill/HorseCollarDE.png@.",
                "Send 1 of the builders to second @lumber_camp/Lumber_camp_aoe2de.png@.",
                "Build @mill/FarmDE.png@ (new @resource/MaleVillDE.jpg@ & from @town_center/Towncenter_aoe2DE.png@), use @resource/Aoe2de_wood.png@ (straggler) if needed.",
                "Second builder builds @other/House_aoe2DE.png@ and @defensive_structures/Palisade_wall_aoe2de.png@.",
                "Produce @stable/Scoutcavalry_aoe2DE.png@ for attack/defense, up to full @defensive_structures/Palisade_wall_aoe2de.png@ (use 2 @resource/MaleVillDE.jpg@ if needed)."
            ]
        },
        {
            "villager_count": 33,
            "age": 2,
            "resources": {
                "wood": 10,
                "food": 16,
                "gold": 7,
                "stone": 0
            },
            "notes": [
                "After 14 @mill/FarmDE.png@, send next 5 @resource/MaleVillDE.jpg@ to @resource/Aoe2de_gold.png@.",
                "Build a @blacksmith/Blacksmith_aoe2de.png@ with the walling @resource/MaleVillDE.jpg@. Research @town_center/WheelbarrowDE.png@.",
                "When depleted, @resource/MaleVillDE.jpg@ from @resource/BerryBushDE.png@ go to @mill/FarmDE.png@ (2) and @resource/Aoe2de_gold.png@ (2).",
                "Build a first @archery_range/Archery_range_aoe2DE.png@ (hidden inside @defensive_structures/Palisade_wall_aoe2de.png@)."
            ]
        },
        {
            "villager_count": 34,
            "age": 3,
            "resources": {
                "wood": 10,
                "food": 16,
                "gold": 8,
                "stone": 0
            },
            "notes": [
                "Add 1 @resource/MaleVillDE.jpg@ to @resource/Aoe2de_gold.png@. Click up to @age/CastleAgeIconDE.png@.",
                "Build a second @archery_range/Archery_range_aoe2DE.png@. Research @mining_camp/GoldMiningDE.png@, @stable/BloodlinesDE.png@ and @blacksmith/FletchingDE.png@."
            ]
        },
        {
            "villager_count": -1,
            "age": 3,
            "resources": {
                "wood": -1,
                "food": -1,
                "gold": -1,
                "stone": -1
            },
            "notes": [
                "Produce @archery_range/Cavalryarcher_aoe2DE.png@ from both @archery_range/Archery_range_aoe2DE.png@. Research @blacksmith/BodkinArrowDE.png@, @lumber_camp/BowSawDE.png@ and @stable/HusbandryDE.png@.",
                "Drop 2 @town_center/Towncenter_aoe2DE.png@ on @resource/Aoe2de_wood.png@ & @resource/Aoe2de_gold.png@ (when you can afford).",
                "Continue booming while massing @archery_range/Cavalryarcher_aoe2DE.png@."
            ]
        }
    ]
}