{
    "name": "man-at-arms into archers",
    "civilization": "Any",
    "author": "Hera",
    "source": "https://discord.com/invite/RdnZdZRkCq (Hera Discord)",
    "build_order": [{
            "villager_count": 6,
            "age": 1,
            "resources": {
                "wood": 0,
                "food": 6,
                "gold": 0,
                "stone": 0
            },
            "notes": [
                "Build 2 @other/House_aoe2DE.png@.",
                "Send the first 6 @resource/MaleVillDE.jpg@ to @animal/Sheep_aoe2DE.png@."
            ]
        },
        {
            "villager_count": 10,
            "age": 1,
            "resources": {
                "wood": 4,
                "food": 6,
                "gold": 0,
                "stone": 0
            },
            "notes": [
                "Build the first @lumber_camp/Lumber_camp_aoe2de.png@.",
                "Send the next 4 @resource/MaleVillDE.jpg@ to @resource/Aoe2de_wood.png@."
            ]
        },
        {
            "villager_count": 11,
            "age": 1,
            "resources": {
                "wood": 4,
                "food": 7,
                "gold": 0,
                "stone": 0
            },
            "notes": [
                "Lure the first @animal/Boar_aoe2DE.png@."
            ]
        },
        {
            "villager_count": 12,
            "age": 1,
            "resources": {
                "wood": 4,
                "food": 8,
                "gold": 0,
                "stone": 0
            },
            "notes": [
                "Build a @other/House_aoe2DE.png@.",
                "Build a @mill/Mill_aoe2de.png@ and gather @resource/BerryBushDE.png@."
            ]
        },
        {
            "villager_count": 14,
            "age": 1,
            "resources": {
                "wood": 4,
                "food": 10,
                "gold": 0,
                "stone": 0
            },
            "notes": [
                "Send 2 @resource/MaleVillDE.jpg@ to @resource/BerryBushDE.png@.",
                "Push 1 @animal/Deer_aoe2DE.png@ with @stable/Scoutcavalry_aoe2DE.png@."
            ]
        },
        {
            "villager_count": 15,
            "age": 1,
            "resources": {
                "wood": 4,
                "food": 11,
                "gold": 0,
                "stone": 0
            },
            "notes": [
                "Lure the second @animal/Boar_aoe2DE.png@."
            ]
        },
        {
            "villager_count": 16,
            "age": 1,
            "resources": {
                "wood": 4,
                "food": 12,
                "gold": 0,
                "stone": 0
            },
            "notes": [
                "Add 1 @resource/MaleVillDE.jpg@ to @resource/BerryBushDE.png@."
            ]
        },
        {
            "villager_count": 17,
            "age": 1,
            "resources": {
                "wood": 4,
                "food": 13,
                "gold": 0,
                "stone": 0
            },
            "notes": [
                "Add 1 @resource/MaleVillDE.jpg@ to @resource/Aoe2de_food.png@ under @town_center/Towncenter_aoe2DE.png@."
            ]
        },
        {
            "villager_count": 18,
            "age": 1,
            "resources": {
                "wood": 4,
                "food": 14,
                "gold": 0,
                "stone": 0
            },
            "notes": [
                "Build a @other/House_aoe2DE.png@, then a @barracks/Barracks_aoe2DE.png@, then another @other/House_aoe2DE.png@.",
                "Once done, send this @resource/MaleVillDE.jpg@ to @resource/Aoe2de_food.png@ under @town_center/Towncenter_aoe2DE.png@."
            ]
        },
        {
            "villager_count": 19,
            "age": 1,
            "resources": {
                "wood": 5,
                "food": 14,
                "gold": 0,
                "stone": 0
            },
            "notes": [
                "Add 1 @resource/MaleVillDE.jpg@ to @resource/Aoe2de_wood.png@."
            ]
        },
        {
            "villager_count": 21,
            "age": 1,
            "resources": {
                "wood": 5,
                "food": 14,
                "gold": 2,
                "stone": 0
            },
            "notes": [
                "Build a @mining_camp/Mining_camp_aoe2de.png@.",
                "Send the next 2 @resource/MaleVillDE.jpg@ to @resource/Aoe2de_gold.png@."
            ]
        },
        {
            "villager_count": 21,
            "age": 2,
            "resources": {
                "wood": 10,
                "food": 9,
                "gold": 2,
                "stone": 0
            },
            "notes": [
                "Research @town_center/LoomDE.png@, then click up to @age/FeudalAgeIconDE.png@.",
                "Send 5 @resource/MaleVillDE.jpg@ from @town_center/Towncenter_aoe2DE.png@ to @resource/Aoe2de_wood.png@ (build second @lumber_camp/Lumber_camp_aoe2de.png@).",
                "Make 3 @barracks/MilitiaDE.png@ and send them forward."
            ]
        },
        {
            "villager_count": 26,
            "age": 2,
            "resources": {
                "wood": 10,
                "food": 9,
                "gold": 7,
                "stone": 0
            },
            "notes": [
                "Research @barracks/ManAtArmsUpgDE.png@, then @lumber_camp/DoubleBitAxe_aoe2DE.png@.",
                "Seed 4-5 @mill/FarmDE.png@ with @resource/MaleVillDE.jpg@ from @town_center/Towncenter_aoe2DE.png@.",
                "Build the first @archery_range/Archery_range_aoe2DE.png@ and send the next 5 @resource/MaleVillDE.jpg@ to @resource/Aoe2de_gold.png@."
            ]
        },
        {
            "villager_count": -1,
            "age": -1,
            "resources": {
                "wood": -1,
                "food": -1,
                "gold": -1,
                "stone": -1
            },
            "notes": [
                "Build a @blacksmith/Blacksmith_aoe2de.png@, and research @blacksmith/FletchingDE.png@.",
                "Keep seeding @mill/FarmDE.png@ and research @town_center/WheelbarrowDE.png@ (around min 16-17).",
                "Click up to @age/CastleAgeIconDE.png@. Build the second @archery_range/Archery_range_aoe2DE.png@ and research @mill/HorseCollarDE.png@."
            ]
        }
    ]
}