{
    "name": "man-at-arms into eagles",
    "civilization": [
        "Aztecs",
        "Incas",
        "Mayans"
    ],
    "author": "Hera",
    "source": "https://discord.com/invite/RdnZdZRkCq (Hera Discord)",
    "build_order": [{
            "villager_count": 6,
            "age": 1,
            "resources": {
                "wood": 0,
                "food": 6,
                "gold": 0,
                "stone": 0
            },
            "notes": [
                "Build 2 @other/House_aoe2DE.png@.",
                "Send the first 6 @resource/MaleVillDE.jpg@ to @animal/Sheep_aoe2DE.png@."
            ]
        },
        {
            "villager_count": 10,
            "age": 1,
            "resources": {
                "wood": 4,
                "food": 6,
                "gold": 0,
                "stone": 0
            },
            "notes": [
                "Build the first @lumber_camp/Lumber_camp_aoe2de.png@.",
                "Send the next 4 @resource/MaleVillDE.jpg@ to @resource/Aoe2de_wood.png@."
            ]
        },
        {
            "villager_count": 11,
            "age": 1,
            "resources": {
                "wood": 4,
                "food": 7,
                "gold": 0,
                "stone": 0
            },
            "notes": [
                "Lure the first @animal/Boar_aoe2DE.png@."
            ]
        },
        {
            "villager_count": 12,
            "age": 1,
            "resources": {
                "wood": 4,
                "food": 8,
                "gold": 0,
                "stone": 0
            },
            "notes": [
                "Build a @other/House_aoe2DE.png@.",
                "Build a @mill/Mill_aoe2de.png@ and gather @resource/BerryBushDE.png@."
            ]
        },
        {
            "villager_count": 14,
            "age": 1,
            "resources": {
                "wood": 4,
                "food": 10,
                "gold": 0,
                "stone": 0
            },
            "notes": [
                "Send 2 @resource/MaleVillDE.jpg@ to @resource/BerryBushDE.png@.",
                "Push 1 @animal/Deer_aoe2DE.png@ with @stable/Scoutcavalry_aoe2DE.png@."
            ]
        },
        {
            "villager_count": 15,
            "age": 1,
            "resources": {
                "wood": 4,
                "food": 11,
                "gold": 0,
                "stone": 0
            },
            "notes": [
                "Lure the second @animal/Boar_aoe2DE.png@."
            ]
        },
        {
            "villager_count": 16,
            "age": 1,
            "resources": {
                "wood": 4,
                "food": 12,
                "gold": 0,
                "stone": 0
            },
            "notes": [
                "Add 1 @resource/MaleVillDE.jpg@ to @resource/BerryBushDE.png@."
            ]
        },
        {
            "villager_count": 17,
            "age": 1,
            "resources": {
                "wood": 4,
                "food": 13,
                "gold": 0,
                "stone": 0
            },
            "notes": [
                "Add 1 @resource/MaleVillDE.jpg@ to @resource/Aoe2de_food.png@ under @town_center/Towncenter_aoe2DE.png@."
            ]
        },
        {
            "villager_count": 18,
            "age": 1,
            "resources": {
                "wood": 4,
                "food": 13,
                "gold": 0,
                "stone": 0
            },
            "notes": [
                "Build a @other/House_aoe2DE.png@, then a @barracks/Barracks_aoe2DE.png@, then another @other/House_aoe2DE.png@.",
                "Once done, start the @defensive_structures/Palisade_wall_aoe2de.png@ with this @resource/MaleVillDE.jpg@."
            ]
        },
        {
            "villager_count": 19,
            "age": 1,
            "resources": {
                "wood": 5,
                "food": 13,
                "gold": 0,
                "stone": 0
            },
            "notes": [
                "Add 1 @resource/MaleVillDE.jpg@ to @resource/Aoe2de_wood.png@."
            ]
        },
        {
            "villager_count": 21,
            "age": 1,
            "resources": {
                "wood": 5,
                "food": 13,
                "gold": 2,
                "stone": 0
            },
            "notes": [
                "Build a @mining_camp/Mining_camp_aoe2de.png@.",
                "Send the next 2 @resource/MaleVillDE.jpg@ to @resource/Aoe2de_gold.png@."
            ]
        },
        {
            "villager_count": 21,
            "age": 2,
            "resources": {
                "wood": 7,
                "food": 10,
                "gold": 3,
                "stone": 0
            },
            "notes": [
                "Research @town_center/LoomDE.png@, then click up to @age/FeudalAgeIconDE.png@.",
                "Send 3 @resource/MaleVillDE.jpg@ from @town_center/Towncenter_aoe2DE.png@ to @resource/Aoe2de_wood.png@ (2, same @lumber_camp/Lumber_camp_aoe2de.png@) and to @resource/Aoe2de_gold.png@ (1).",
                "Make 3 @barracks/MilitiaDE.png@ and send them forward."
            ]
        },
        {
            "villager_count": 24,
            "age": 2,
            "resources": {
                "wood": 7,
                "food": 10,
                "gold": 6,
                "stone": 0
            },
            "notes": [
                "Research @barracks/ManAtArmsUpgDE.png@, then @lumber_camp/DoubleBitAxe_aoe2DE.png@ and @mill/HorseCollarDE.png@.",
                "Build the second @barracks/Barracks_aoe2DE.png@ with the walling @resource/MaleVillDE.jpg@.",
                "Seed the next 3 @resource/MaleVillDE.jpg@ to @resource/Aoe2de_gold.png@."
            ]
        },
        {
            "villager_count": 28,
            "age": 2,
            "resources": {
                "wood": 7,
                "food": 14,
                "gold": 6,
                "stone": 0
            },
            "notes": [
                "Seed @mill/FarmDE.png@ with @resource/MaleVillDE.jpg@ from @town_center/Towncenter_aoe2DE.png@, until you have 10 of them."
            ]
        },
        {
            "villager_count": -1,
            "age": 3,
            "resources": {
                "wood": -1,
                "food": -1,
                "gold": -1,
                "stone": -1
            },
            "notes": [
                "Build a @blacksmith/Blacksmith_aoe2de.png@, and research @blacksmith/Forging_aoe2de.png@ and @blacksmith/ScaleMailArmorDE.png@.",
                "Next @resource/MaleVillDE.jpg@ go to @resource/Aoe2de_gold.png@ (no new @mill/FarmDE.png@).",
                "When @resource/BerryBushDE.png@ run out, send those @resource/MaleVillDE.jpg@ to @resource/Aoe2de_wood.png@ and @resource/Aoe2de_gold.png@.",
                "Build a @market/Market_aoe2DE.png@, keep making @barracks/Eaglescout_aoe2DE.png@ (buy @resource/Aoe2de_food.png@ with extra @resource/Aoe2de_gold.png@ or @resource/Aoe2de_stone.png@).",
                "Click up to @age/CastleAgeIconDE.png@. Build third @barracks/Barracks_aoe2DE.png@ and keep massing @barracks/Eaglescout_aoe2DE.png@.",
                "Build a second @mining_camp/Mining_camp_aoe2de.png@ and research @mining_camp/GoldMiningDE.png@."
            ]
        },
        {
            "villager_count": -1,
            "age": -1,
            "resources": {
                "wood": -1,
                "food": -1,
                "gold": -1,
                "stone": -1
            },
            "notes": [
                "Reasearch @barracks/EagleWarriorUpgDE.png@, @blacksmith/IronCastingDE.png@, @blacksmith/ChainMailArmorDE.png@, @lumber_camp/BowSawDE.png@ and @barracks/SquiresDE.png@.",
                "Keep massing @barracks/Eaglewarrior_aoe2DE.png@ and add more @barracks/Barracks_aoe2DE.png@. Build a new @mining_camp/Mining_camp_aoe2de.png@.",
                "Add @monastery/Monk_aoe2DE.png@ and/or @siege_workshop/Siege_workshop_aoe2DE.png@ to continue the push."
            ]
        }
    ]
}