{
    "name": "poles man-at-arms towers",
    "civilization": "Poles",
    "author": "Hera",
    "source": "https://discord.com/invite/RdnZdZRkCq (Hera Discord)",
    "build_order": [{
            "villager_count": 6,
            "age": 1,
            "resources": {
                "wood": 0,
                "food": 6,
                "gold": 0,
                "stone": 0
            },
            "notes": [
                "Build 2 @other/House_aoe2DE.png@.",
                "Send the first 6 @resource/MaleVillDE.jpg@ to @animal/Sheep_aoe2DE.png@."
            ]
        },
        {
            "villager_count": 9,
            "age": 1,
            "resources": {
                "wood": 3,
                "food": 6,
                "gold": 0,
                "stone": 0
            },
            "notes": [
                "Build the first @lumber_camp/Lumber_camp_aoe2de.png@.",
                "Send the next 3 @resource/MaleVillDE.jpg@ to @resource/Aoe2de_wood.png@."
            ]
        },
        {
            "villager_count": 10,
            "age": 1,
            "resources": {
                "wood": 3,
                "food": 7,
                "gold": 0,
                "stone": 0
            },
            "notes": [
                "Lure the first @animal/Boar_aoe2DE.png@."
            ]
        },
        {
            "villager_count": 11,
            "age": 1,
            "resources": {
                "wood": 3,
                "food": 8,
                "gold": 0,
                "stone": 0
            },
            "notes": [
                "Add 1 @resource/MaleVillDE.jpg@ to @resource/Aoe2de_food.png@ under @town_center/Towncenter_aoe2DE.png@."
            ]
        },
        {
            "villager_count": 12,
            "age": 1,
            "resources": {
                "wood": 3,
                "food": 9,
                "gold": 0,
                "stone": 0
            },
            "notes": [
                "Build a @other/House_aoe2DE.png@, then a @mill/Aoe2-icon--folwark.png@ near @resource/BerryBushDE.png@."
            ]
        },
        {
            "villager_count": 13,
            "age": 1,
            "resources": {
                "wood": 3,
                "food": 10,
                "gold": 0,
                "stone": 0
            },
            "notes": [
                "Lure the second @animal/Boar_aoe2DE.png@."
            ]
        },
        {
            "villager_count": 16,
            "age": 1,
            "resources": {
                "wood": 3,
                "food": 13,
                "gold": 0,
                "stone": 0
            },
            "notes": [
                "Add 3 @resource/MaleVillDE.jpg@ to @resource/BerryBushDE.png@."
            ]
        },
        {
            "villager_count": 18,
            "age": 1,
            "resources": {
                "wood": 3,
                "food": 15,
                "gold": 0,
                "stone": 0
            },
            "notes": [
                "Add 2 @resource/MaleVillDE.jpg@ to @resource/Aoe2de_food.png@ under @town_center/Towncenter_aoe2DE.png@."
            ]
        },
        {
            "villager_count": 19,
            "age": 1,
            "resources": {
                "wood": 4,
                "food": 15,
                "gold": 0,
                "stone": 0
            },
            "notes": [
                "Add 1 @resource/MaleVillDE.jpg@ to @resource/Aoe2de_wood.png@."
            ]
        },
        {
            "villager_count": 21,
            "age": 1,
            "resources": {
                "wood": 4,
                "food": 15,
                "gold": 0,
                "stone": 2
            },
            "notes": [
                "Send next 2 @resource/MaleVillDE.jpg@ to @resource/Aoe2de_stone.png@ (build @mining_camp/Mining_camp_aoe2de.png@)."
            ]
        },
        {
            "villager_count": 21,
            "age": 2,
            "resources": {
                "wood": 4,
                "food": 9,
                "gold": 0,
                "stone": 4
            },
            "notes": [
                "Research @town_center/LoomDE.png@, then click up to @age/FeudalAgeIconDE.png@.",
                "Directly build @other/House_aoe2DE.png@ and @barracks/Barracks_aoe2DE.png@ (front) with 4 @resource/MaleVillDE.jpg@ from @town_center/Towncenter_aoe2DE.png@.",
                "Send these 4 @resource/MaleVillDE.jpg@ forward and queue up to 4 @barracks/MilitiaDE.png@.",
                "Send 2 @resource/MaleVillDE.jpg@ from @town_center/Towncenter_aoe2DE.png@ to @resource/Aoe2de_stone.png@."
            ]
        },
        {
            "villager_count": -1,
            "age": 2,
            "resources": {
                "wood": -1,
                "food": -1,
                "gold": -1,
                "stone": -1
            },
            "notes": [
                "Research @barracks/ManAtArmsUpgDE.png@. Skip @lumber_camp/DoubleBitAxe_aoe2DE.png@ and @mill/HorseCollarDE.png@ for now.",
                "Build a @defensive_structures/Tower_aoe2de.png@ near a key resource being collected.",
                "Force fights with @barracks/Manatarms_aoe2DE.png@, @stable/Scoutcavalry_aoe2DE.png@ and @resource/MaleVillDE.jpg@.",
                "Build @mill/FarmDE.png@ around @mill/Aoe2-icon--folwark.png@ once @animal/Sheep_aoe2DE.png@ are depleted.",
                "Attack opponent @resource/MaleVillDE.jpg@ or buildings with your @barracks/Manatarms_aoe2DE.png@."
            ]
        }
    ]
}