{
    "name": "pre-mill drush fast castle",
    "civilization": "Any",
    "author": "Hera",
    "source": "https://discord.com/invite/RdnZdZRkCq (Hera Discord)",
    "build_order": [{
            "villager_count": 6,
            "age": 1,
            "resources": {
                "wood": 0,
                "food": 6,
                "gold": 0,
                "stone": 0
            },
            "notes": [
                "Build 2 @other/House_aoe2DE.png@.",
                "Send the first 6 @resource/MaleVillDE.jpg@ to @animal/Sheep_aoe2DE.png@."
            ]
        },
        {
            "villager_count": 10,
            "age": 1,
            "resources": {
                "wood": 4,
                "food": 6,
                "gold": 0,
                "stone": 0
            },
            "notes": [
                "Build the first @lumber_camp/Lumber_camp_aoe2de.png@.",
                "Send the next 4 @resource/MaleVillDE.jpg@ to @resource/Aoe2de_wood.png@."
            ]
        },
        {
            "villager_count": 11,
            "age": 1,
            "resources": {
                "wood": 4,
                "food": 7,
                "gold": 0,
                "stone": 0
            },
            "notes": [
                "Lure the first @animal/Boar_aoe2DE.png@."
            ]
        },
        {
            "villager_count": 12,
            "age": 1,
            "resources": {
                "wood": 4,
                "food": 8,
                "gold": 0,
                "stone": 0
            },
            "notes": [
                "Next @resource/MaleVillDE.jpg@ builds a @other/House_aoe2DE.png@, then a @barracks/Barracks_aoe2DE.png@.",
                "Once done, start gathering @resource/BerryBushDE.png@ with this @resource/MaleVillDE.jpg@."
            ]
        },
        {
            "villager_count": 13,
            "age": 1,
            "resources": {
                "wood": 4,
                "food": 9,
                "gold": 0,
                "stone": 0
            },
            "notes": [
                "Lure the second @animal/Boar_aoe2DE.png@."
            ]
        },
        {
            "villager_count": 14,
            "age": 1,
            "resources": {
                "wood": 4,
                "food": 9,
                "gold": 1,
                "stone": 0
            },
            "notes": [
                "Next @resource/MaleVillDE.jpg@ mines 10 @resource/Aoe2de_gold.png@ without building @mining_camp/Mining_camp_aoe2de.png@.",
                "Once done, start the @defensive_structures/Palisade_wall_aoe2de.png@ with this @resource/MaleVillDE.jpg@."
            ]
        },
        {
            "villager_count": 17,
            "age": 1,
            "resources": {
                "wood": 4,
                "food": 12,
                "gold": 0,
                "stone": 0
            },
            "notes": [
                "Make 3 @barracks/MilitiaDE.png@ and send them forward (when all ready).",
                "Do not idle the @town_center/Towncenter_aoe2DE.png@.",
                "Add 3 @resource/MaleVillDE.jpg@ to @resource/BerryBushDE.png@, building a @mill/Mill_aoe2de.png@."
            ]
        },
        {
            "villager_count": 19,
            "age": 1,
            "resources": {
                "wood": 5,
                "food": 12,
                "gold": 0,
                "stone": 0
            },
            "notes": [
                "Add 1 @resource/MaleVillDE.jpg@ to the first @lumber_camp/Lumber_camp_aoe2de.png@.",
                "The next one helps with the @defensive_structures/Palisade_wall_aoe2de.png@."
            ]
        },
        {
            "villager_count": 24,
            "age": 1,
            "resources": {
                "wood": 10,
                "food": 12,
                "gold": 0,
                "stone": 0
            },
            "notes": [
                "Build a second @lumber_camp/Lumber_camp_aoe2de.png@.",
                "Send the next 5 @resource/MaleVillDE.jpg@ to @resource/Aoe2de_wood.png@."
            ]
        },
        {
            "villager_count": 25,
            "age": 1,
            "resources": {
                "wood": 10,
                "food": 13,
                "gold": 0,
                "stone": 0
            },
            "notes": [
                "Add 1 @resource/MaleVillDE.jpg@ to @resource/BerryBushDE.png@.",
                "Make @mill/FarmDE.png@ with @resource/MaleVillDE.jpg@ from @resource/Aoe2de_food.png@, until you have 7-8."
            ]
        },
        {
            "villager_count": 29,
            "age": 1,
            "resources": {
                "wood": 10,
                "food": 13,
                "gold": 4,
                "stone": 0
            },
            "notes": [
                "Build a@mining_camp/Mining_camp_aoe2de.png@.",
                "Send the next 4 @resource/MaleVillDE.jpg@ to @resource/Aoe2de_gold.png@."
            ]
        },
        {
            "villager_count": 29,
            "age": 2,
            "resources": {
                "wood": 10,
                "food": 13,
                "gold": 4,
                "stone": 0
            },
            "notes": [
                "Research @town_center/LoomDE.png@, then click up to @age/FeudalAgeIconDE.png@.",
                "Continue the @defensive_structures/Palisade_wall_aoe2de.png@."
            ]
        },
        {
            "villager_count": 31,
            "age": 2,
            "resources": {
                "wood": 10,
                "food": 13,
                "gold": 6,
                "stone": 0
            },
            "notes": [
                "Build a @blacksmith/Blacksmith_aoe2de.png@ and a first @archery_range/Archery_range_aoe2DE.png@ (or @stable/Stable_aoe2DE.png@).",
                "Add 2 @resource/MaleVillDE.jpg@ to @resource/Aoe2de_gold.png@."
            ]
        },
        {
            "villager_count": 31,
            "age": 3,
            "resources": {
                "wood": 10,
                "food": 13,
                "gold": 8,
                "stone": 0
            },
            "notes": [
                "Click up to @age/CastleAgeIconDE.png@. Research @lumber_camp/DoubleBitAxe_aoe2DE.png@ and @mill/HorseCollarDE.png@.",
                "Send the 2 @resource/MaleVillDE.jpg@ from @defensive_structures/Palisade_wall_aoe2de.png@ to @resource/Aoe2de_gold.png@ (when fully walled).",
                "Build a second @archery_range/Archer_aoe2DE.png@ (or @stable/Stable_aoe2DE.png@).",
                "Produce @archery_range/Archer_aoe2DE.png@ and reasearch @blacksmith/FletchingDE.png@ (if applicable).",
                "Seed @mill/FarmDE.png@, send extra @resource/MaleVillDE.jpg@ to @resource/Aoe2de_wood.png@."
            ]
        },
        {
            "villager_count": -1,
            "age": -1,
            "resources": {
                "wood": -1,
                "food": -1,
                "gold": -1,
                "stone": -1
            },
            "notes": [
                "Research @archery_range/ArbalestDE.png@ and @blacksmith/BodkinArrowDE.png@ (if applicable).",
                "Research @lumber_camp/BowSawDE.png@ and @town_center/WheelbarrowDE.png@."
            ]
        }
    ]
}