{
    "name": "saracens drush fc market",
    "civilization": "Saracens",
    "author": "Hera",
    "source": "https://discord.com/invite/RdnZdZRkCq (Hera Discord)",
    "build_order": [{
            "villager_count": 6,
            "age": 1,
            "resources": {
                "wood": 0,
                "food": 6,
                "gold": 0,
                "stone": 0
            },
            "notes": [
                "Build 2 @other/House_aoe2DE.png@.",
                "Send the first 6 @resource/MaleVillDE.jpg@ to @animal/Sheep_aoe2DE.png@."
            ]
        },
        {
            "villager_count": 10,
            "age": 1,
            "resources": {
                "wood": 4,
                "food": 6,
                "gold": 0,
                "stone": 0
            },
            "notes": [
                "Build the first @lumber_camp/Lumber_camp_aoe2de.png@.",
                "Send the next 4 @resource/MaleVillDE.jpg@ to @resource/Aoe2de_wood.png@."
            ]
        },
        {
            "villager_count": 11,
            "age": 1,
            "resources": {
                "wood": 4,
                "food": 7,
                "gold": 0,
                "stone": 0
            },
            "notes": [
                "Lure the first @animal/Boar_aoe2DE.png@."
            ]
        },
        {
            "villager_count": 12,
            "age": 1,
            "resources": {
                "wood": 4,
                "food": 8,
                "gold": 0,
                "stone": 0
            },
            "notes": [
                "Build a @other/House_aoe2DE.png@.",
                "Build a @mill/Mill_aoe2de.png@ and gather @resource/BerryBushDE.png@."
            ]
        },
        {
            "villager_count": 14,
            "age": 1,
            "resources": {
                "wood": 4,
                "food": 10,
                "gold": 0,
                "stone": 0
            },
            "notes": [
                "Send 2 @resource/MaleVillDE.jpg@ to @resource/BerryBushDE.png@."
            ]
        },
        {
            "villager_count": 15,
            "age": 1,
            "resources": {
                "wood": 4,
                "food": 11,
                "gold": 0,
                "stone": 0
            },
            "notes": [
                "Lure the second @animal/Boar_aoe2DE.png@."
            ]
        },
        {
            "villager_count": 16,
            "age": 1,
            "resources": {
                "wood": 4,
                "food": 12,
                "gold": 0,
                "stone": 0
            },
            "notes": [
                "Add 1 @resource/MaleVillDE.jpg@ to @resource/BerryBushDE.png@."
            ]
        },
        {
            "villager_count": 17,
            "age": 1,
            "resources": {
                "wood": 4,
                "food": 12,
                "gold": 0,
                "stone": 0
            },
            "notes": [
                "Next @resource/MaleVillDE.jpg@ builds a @other/House_aoe2DE.png@, then a @barracks/Barracks_aoe2DE.png@, then another @other/House_aoe2DE.png@.",
                "Once done, this @resource/MaleVillDE.jpg@ goes to @resource/Aoe2de_food.png@ under @town_center/Towncenter_aoe2DE.png@."
            ]
        },
        {
            "villager_count": 18,
            "age": 1,
            "resources": {
                "wood": 4,
                "food": 12,
                "gold": 1,
                "stone": 0
            },
            "notes": [
                "Next @resource/MaleVillDE.jpg@ mines 10 @resource/Aoe2de_gold.png@ without building @mining_camp/Mining_camp_aoe2de.png@.",
                "Once done, send this @resource/MaleVillDE.jpg@ to @resource/Aoe2de_food.png@ under @town_center/Towncenter_aoe2DE.png@."
            ]
        },
        {
            "villager_count": 22,
            "age": 1,
            "resources": {
                "wood": 8,
                "food": 14,
                "gold": 0,
                "stone": 0
            },
            "notes": [
                "Make 3 @barracks/MilitiaDE.png@ and send them forward with the @stable/Scoutcavalry_aoe2DE.png@.",
                "Add 4 @resource/MaleVillDE.jpg@ to @resource/Aoe2de_wood.png@ (build second @lumber_camp/Lumber_camp_aoe2de.png@ with new @resource/MaleVillDE.jpg@)."
            ]
        },
        {
            "villager_count": 24,
            "age": 1,
            "resources": {
                "wood": 8,
                "food": 16,
                "gold": 0,
                "stone": 0
            },
            "notes": [
                "Next 2 @resource/MaleVillDE.jpg@ go to @resource/Aoe2de_food.png@ under @town_center/Towncenter_aoe2DE.png@ (6 @resource/MaleVillDE.jpg@ on @animal/Sheep_aoe2DE.png@, others on @mill/FarmDE.png@)."
            ]
        },
        {
            "villager_count": 27,
            "age": 2,
            "resources": {
                "wood": 8,
                "food": 16,
                "gold": 3,
                "stone": 0
            },
            "notes": [
                "Build a @mining_camp/Mining_camp_aoe2de.png@. Add 3 @resource/MaleVillDE.jpg@ to @resource/Aoe2de_gold.png@.",
                "Research @town_center/LoomDE.png@, then click up to @age/FeudalAgeIconDE.png@."
            ]
        },
        {
            "villager_count": 29,
            "age": 2,
            "resources": {
                "wood": 8,
                "food": 16,
                "gold": 5,
                "stone": 0
            },
            "notes": [
                "Build 1 @archery_range/Archery_range_aoe2DE.png@ and 1 @market/Market_aoe2DE.png@ (2 @resource/MaleVillDE.jpg@ on each).",
                "Send 2 new @resource/MaleVillDE.jpg@ (+ @resource/MaleVillDE.jpg@ from depleted @resource/BerryBushDE.png@) to @resource/Aoe2de_gold.png@."
            ]
        },
        {
            "villager_count": 29,
            "age": 3,
            "resources": {
                "wood": 8,
                "food": 16,
                "gold": 5,
                "stone": 0
            },
            "notes": [
                "Sell @resource/Aoe2de_stone.png@ and click up to @age/CastleAgeIconDE.png@.",
                "Research @lumber_camp/DoubleBitAxe_aoe2DE.png@. Produce @archery_range/Archer_aoe2DE.png@ and build second @archery_range/Archery_range_aoe2DE.png@."
            ]
        },
        {
            "villager_count": 34,
            "age": 3,
            "resources": {
                "wood": 10,
                "food": 16,
                "gold": 8,
                "stone": 0
            },
            "notes": [
                "Research @archery_range/ArbalestDE.png@ and @blacksmith/BodkinArrowDE.png@.",
                "Add 2 @resource/MaleVillDE.jpg@ to @resource/Aoe2de_wood.png@ and 3 @resource/MaleVillDE.jpg@ to @resource/Aoe2de_gold.png@."
            ]
        },
        {
            "villager_count": -1,
            "age": 3,
            "resources": {
                "wood": -1,
                "food": -1,
                "gold": -1,
                "stone": -1
            },
            "notes": [
                "Build a @university/University_AoE2_DE.png@ and research @university/BallisticsDE.png@.",
                "Abuse the @market/Market_aoe2DE.png@. Research @lumber_camp/BowSawDE.png@."
            ]
        }
    ]
}