{
    "name": "scouts into knights",
    "civilization": "Any",
    "author": "Hera",
    "source": "https://discord.com/invite/RdnZdZRkCq (Hera Discord)",
    "build_order": [{
            "villager_count": 6,
            "age": 1,
            "resources": {
                "wood": 0,
                "food": 6,
                "gold": 0,
                "stone": 0
            },
            "notes": [
                "Build 2 @other/House_aoe2DE.png@.",
                "Send the fitst 6 @resource/MaleVillDE.jpg@ to @animal/Sheep_aoe2DE.png@."
            ]
        },
        {
            "villager_count": 9,
            "age": 1,
            "resources": {
                "wood": 3,
                "food": 6,
                "gold": 0,
                "stone": 0
            },
            "notes": [
                "Build the first @lumber_camp/Lumber_camp_aoe2de.png@.",
                "Send the next 3 @resource/MaleVillDE.jpg@ to @resource/Aoe2de_wood.png@."
            ]
        },
        {
            "villager_count": 10,
            "age": 1,
            "resources": {
                "wood": 3,
                "food": 7,
                "gold": 0,
                "stone": 0
            },
            "notes": [
                "Lure the first @animal/Boar_aoe2DE.png@."
            ]
        },
        {
            "villager_count": 11,
            "age": 1,
            "resources": {
                "wood": 3,
                "food": 8,
                "gold": 0,
                "stone": 0
            },
            "notes": [
                "Next @resource/MaleVillDE.jpg@ go to @resource/Aoe2de_food.png@ under @town_center/Towncenter_aoe2DE.png@."
            ]
        },
        {
            "villager_count": 12,
            "age": 1,
            "resources": {
                "wood": 3,
                "food": 9,
                "gold": 0,
                "stone": 0
            },
            "notes": [
                "Build a @other/House_aoe2DE.png@.",
                "Build a @mill/Mill_aoe2de.png@ and gather @resource/BerryBushDE.png@."
            ]
        },
        {
            "villager_count": 14,
            "age": 1,
            "resources": {
                "wood": 3,
                "food": 11,
                "gold": 0,
                "stone": 0
            },
            "notes": [
                "Send 2 @resource/MaleVillDE.jpg@ to @resource/BerryBushDE.png@."
            ]
        },
        {
            "villager_count": 15,
            "age": 1,
            "resources": {
                "wood": 3,
                "food": 12,
                "gold": 0,
                "stone": 0
            },
            "notes": [
                "Lure the second @animal/Boar_aoe2DE.png@."
            ]
        },
        {
            "villager_count": 16,
            "age": 1,
            "resources": {
                "wood": 3,
                "food": 13,
                "gold": 0,
                "stone": 0
            },
            "notes": [
                "Add 1 @resource/MaleVillDE.jpg@ to @resource/BerryBushDE.png@."
            ]
        },
        {
            "villager_count": 17,
            "age": 1,
            "resources": {
                "wood": 3,
                "food": 14,
                "gold": 0,
                "stone": 0
            },
            "notes": [
                "Add 1 @resource/MaleVillDE.jpg@ to @resource/Aoe2de_food.png@ under @town_center/Towncenter_aoe2DE.png@."
            ]
        },
        {
            "villager_count": 19,
            "age": 1,
            "resources": {
                "wood": 5,
                "food": 14,
                "gold": 0,
                "stone": 0
            },
            "notes": [
                "Add 2 @resource/MaleVillDE.jpg@ to @resource/Aoe2de_wood.png@."
            ]
        },
        {
            "villager_count": 20,
            "age": 1,
            "resources": {
                "wood": 6,
                "food": 14,
                "gold": 0,
                "stone": 0
            },
            "notes": [
                "Build a second @lumber_camp/Lumber_camp_aoe2de.png@.",
                "Add 1 @resource/MaleVillDE.jpg@ to @resource/Aoe2de_wood.png@."
            ]
        },
        {
            "villager_count": 20,
            "age": 2,
            "resources": {
                "wood": 9,
                "food": 11,
                "gold": 0,
                "stone": 0
            },
            "notes": [
                "Research @town_center/LoomDE.png@, then click up to @age/FeudalAgeIconDE.png@.",
                "Send 3 @resource/MaleVillDE.jpg@ from @town_center/Towncenter_aoe2DE.png@ to @lumber_camp/Lumber_camp_aoe2de.png@.",
                "Build @barracks/Barracks_aoe2DE.png@ at 60% up."
            ]
        },
        {
            "villager_count": 21,
            "age": 2,
            "resources": {
                "wood": 10,
                "food": 11,
                "gold": 0,
                "stone": 0
            },
            "notes": [
                "Build a @stable/Stable_aoe2DE.png@ (with 2 @resource/MaleVillDE.jpg@) and make @stable/Scoutcavalry_aoe2DE.png@.",
                "Research @lumber_camp/DoubleBitAxe_aoe2DE.png@ and @mill/HorseCollarDE.png@.",
                "Send 1 extra @resource/MaleVillDE.jpg@ to @resource/Aoe2de_wood.png@."
            ]
        },
        {
            "villager_count": 28,
            "age": 2,
            "resources": {
                "wood": 10,
                "food": 18,
                "gold": 0,
                "stone": 0
            },
            "notes": [
                "Next @resource/MaleVillDE.jpg@ go to @resource/Aoe2de_wood.png@ (straggler) and then make @mill/FarmDE.png@."
            ]
        },
        {
            "villager_count": 33,
            "age": 2,
            "resources": {
                "wood": 10,
                "food": 18,
                "gold": 5,
                "stone": 0
            },
            "notes": [
                "Next 5 @resource/MaleVillDE.jpg@ go to @resource/Aoe2de_gold.png@."
            ]
        },
        {
            "villager_count": 33,
            "age": 3,
            "resources": {
                "wood": 10,
                "food": 18,
                "gold": 5,
                "stone": 0
            },
            "notes": [
                "Build a @blacksmith/Blacksmith_aoe2de.png@ and research @town_center/WheelbarrowDE.png@.",
                "Send @resource/MaleVillDE.jpg@ from @resource/BerryBushDE.png@ to @mill/FarmDE.png@ (when depleted).",
                "Click up to @age/CastleAgeIconDE.png@.",
                "Research @stable/BloodlinesDE.png@, @blacksmith/ScaleBardingArmorDE.png@, @mining_camp/GoldMiningDE.png@ and build a second @stable/Stable_aoe2DE.png@."
            ]
        },
        {
            "villager_count": -1,
            "age": -1,
            "resources": {
                "wood": 10,
                "food": 18,
                "gold": 5,
                "stone": 0
            },
            "notes": [
                "Produce @stable/Knight_aoe2DE.png@, drop 2 @town_center/Towncenter_aoe2DE.png@ and research @lumber_camp/BowSawDE.png@."
            ]
        }
    ]
}