{
    "name": "straight archers",
    "civilization": "Any",
    "author": "Hera",
    "source": "https://discord.com/invite/RdnZdZRkCq (Hera Discord)",
    "build_order": [{
            "villager_count": 6,
            "age": 1,
            "resources": {
                "wood": 0,
                "food": 6,
                "gold": 0,
                "stone": 0
            },
            "notes": [
                "Build 2 @other/House_aoe2DE.png@.",
                "Send the first 6 @resource/MaleVillDE.jpg@ to @animal/Sheep_aoe2DE.png@."
            ]
        },
        {
            "villager_count": 10,
            "age": 1,
            "resources": {
                "wood": 4,
                "food": 6,
                "gold": 0,
                "stone": 0
            },
            "notes": [
                "Build the first @lumber_camp/Lumber_camp_aoe2de.png@.",
                "Send the next 4 @resource/MaleVillDE.jpg@ to @resource/Aoe2de_wood.png@."
            ]
        },
        {
            "villager_count": 11,
            "age": 1,
            "resources": {
                "wood": 4,
                "food": 7,
                "gold": 0,
                "stone": 0
            },
            "notes": [
                "Lure the first @animal/Boar_aoe2DE.png@."
            ]
        },
        {
            "villager_count": 12,
            "age": 1,
            "resources": {
                "wood": 4,
                "food": 8,
                "gold": 0,
                "stone": 0
            },
            "notes": [
                "Build a @other/House_aoe2DE.png@.",
                "Build a @mill/Mill_aoe2de.png@ and gather @resource/BerryBushDE.png@."
            ]
        },
        {
            "villager_count": 14,
            "age": 1,
            "resources": {
                "wood": 4,
                "food": 10,
                "gold": 0,
                "stone": 0
            },
            "notes": [
                "Send 2 @resource/MaleVillDE.jpg@ to @resource/BerryBushDE.png@."
            ]
        },
        {
            "villager_count": 15,
            "age": 1,
            "resources": {
                "wood": 4,
                "food": 11,
                "gold": 0,
                "stone": 0
            },
            "notes": [
                "Lure the second @animal/Boar_aoe2DE.png@."
            ]
        },
        {
            "villager_count": 16,
            "age": 1,
            "resources": {
                "wood": 4,
                "food": 12,
                "gold": 0,
                "stone": 0
            },
            "notes": [
                "Add 1 @resource/MaleVillDE.jpg@ to @resource/BerryBushDE.png@."
            ]
        },
        {
            "villager_count": 18,
            "age": 1,
            "resources": {
                "wood": 4,
                "food": 14,
                "gold": 0,
                "stone": 0
            },
            "notes": [
                "Add 2 @resource/MaleVillDE.jpg@ to @resource/Aoe2de_food.png@ under @town_center/Towncenter_aoe2DE.png@."
            ]
        },
        {
            "villager_count": 19,
            "age": 1,
            "resources": {
                "wood": 5,
                "food": 14,
                "gold": 0,
                "stone": 0
            },
            "notes": [
                "Add 1 @resource/MaleVillDE.jpg@ to @resource/Aoe2de_wood.png@."
            ]
        },
        {
            "villager_count": 21,
            "age": 1,
            "resources": {
                "wood": 7,
                "food": 14,
                "gold": 0,
                "stone": 0
            },
            "notes": [
                "Build a second @lumber_camp/Lumber_camp_aoe2de.png@.",
                "Add 2 @resource/MaleVillDE.jpg@ to @resource/Aoe2de_wood.png@."
            ]
        },
        {
            "villager_count": 21,
            "age": 2,
            "resources": {
                "wood": 10,
                "food": 8,
                "gold": 3,
                "stone": 0
            },
            "notes": [
                "Research @town_center/LoomDE.png@, then click up to @age/FeudalAgeIconDE.png@.",
                "Send 6 @resource/MaleVillDE.jpg@ from @town_center/Towncenter_aoe2DE.png@ to @lumber_camp/Lumber_camp_aoe2de.png@ (3) and to @mining_camp/Mining_camp_aoe2de.png@ (3).",
                "Build @barracks/Barracks_aoe2DE.png@ at 60% up."
            ]
        },
        {
            "villager_count": 25,
            "age": 2,
            "resources": {
                "wood": 10,
                "food": 8,
                "gold": 7,
                "stone": 0
            },
            "notes": [
                "Research @lumber_camp/DoubleBitAxe_aoe2DE.png@, build 2 @archery_range/Archery_range_aoe2DE.png@ and make @archery_range/Archer_aoe2DE.png@.",
                "Send the next @resource/MaleVillDE.jpg@ to @resource/Aoe2de_gold.png@."
            ]
        },
        {
            "villager_count": -1,
            "age": 3,
            "resources": {
                "wood": 10,
                "food": -1,
                "gold": 8,
                "stone": 0
            },
            "notes": [
                "Build a @blacksmith/Blacksmith_aoe2de.png@, continue walling.",
                "All new @resource/MaleVillDE.jpg@ go to @resource/Aoe2de_wood.png@ (straggler) and then make @mill/FarmDE.png@.",
                "Get @blacksmith/FletchingDE.png@ and @town_center/WheelbarrowDE.png@ (16-17 @resource/MaleVillDE.jpg@). Move @archery_range/Archer_aoe2DE.png@ out.",
                "Send 1 @resource/MaleVillDE.jpg@ to @resource/Aoe2de_gold.png@ and click up to @age/CastleAgeIconDE.png@.",
                "Research @mill/HorseCollarDE.png@, @mining_camp/GoldMiningDE.png@, @blacksmith/PaddedArcherArmorDE.png@."
            ]
        },
        {
            "villager_count": -1,
            "age": -1,
            "resources": {
                "wood": 10,
                "food": -1,
                "gold": 8,
                "stone": 0
            },
            "notes": [
                "Research @archery_range/ArbalestDE.png@, @blacksmith/BodkinArrowDE.png@ and @lumber_camp/BowSawDE.png@.",
                "Drop 2 @town_center/Towncenter_aoe2DE.png@, build a @university/University_AoE2_DE.png@ and research @university/BallisticsDE.png@."
            ]
        }
    ]
}